{
  "result": {
    "meta": {
      "totalCount": 5,
      "count": 5,
      "request": {
        "offset": 0,
        "limit": 100,
        "boundary": {
          "minX": 128.8761,
          "minY": 37.75640450450451,
          "maxX": 128.88179707799122,
          "maxY": 37.76090900900901
        },
        "code": "01",
        "sortType": "RECOMMEND",
        "timeCode": "AFTERNOON",
        "searchCoord": "128.87894853899562;37.758656756756764",
        "adultCheckBean": {
          "isLogin": false,
          "isAdult": false,
          "isAdultContentAllowed": false
        },
        "hasReservation": false,
        "multilingualType": "KOREAN"
      },
      "recommendationCode": null,
      "radius": null
    },
    "list": [
      {
        "rank": 1,
        "id": "1789936692",
        "name": "카페무무",
        "x": "128.8815694",
        "y": "37.7582479",
        "distance": 0.235,
        "categoryName": "디저트",
        "categoryPath": [
          [
            "220036",
            "220052",
            "220563"
          ]
        ],
        "category": [
          "음식점",
          "카페,디저트"
        ],
        "reviewCount": 64,
        "averagePrice": 5000,
        "address": "강원특별자치도 강릉시 교동 1730-9 1층",
        "roadAddress": "강원특별자치도 강릉시 원대로 39",
        "abbrAddress": "교동 1730-9 1층",
        "shortAddress": [
          "강원 강릉시",
          "원대로 39"
        ],
        "displayContext": [],
        "labelTheme": "카페",
        "microReviews": [],
        "cardDescription": "매장 앞 도로변 주차 가능, 애견동반 가능, 단체예약 가능.",
        "description": "매장 앞 도로변 주차 가능, 애견동반 가능, 단체예약 가능.",
        "images": [
          "https://pup-review-phinf.pstatic.net/MjAyNTA2MjVfMTcx/MDAxNzUwODQ4MzYzODMw.FH9RRtPaB6eQq043Y6B28I62yaW0xqmFzoIpz-l4Fqwg.BgdC8bp1wizC_z0cRGgzvNP_C8H5bl7AGq9yFXw9zqQg.JPEG/20250625_114311.jpg.jpg",
          "https://pup-review-phinf.pstatic.net/MjAyNTA0MTVfODQg/MDAxNzQ0Njk4NTUwMDE2.PD4XZlFcwYA5azbvdtDxy-RZ9pgz4qVgw31iBWzBCPAg.YxnoZgpfDe7DjnmMWl4wWWxBfT8MiyT56Z7HQXkk98og.JPEG/20250415_152701.jpg.jpg",
          "https://ldb-phinf.pstatic.net/20220425_182/1650880041789mKrV1_PNG/%B7%CE%B0%ED.png"
        ],
        "marker": "nres://marker/00079-00145",
        "markerSelected": "nres://marker/00079-00309",
        "markerId": "220563",
        "bizhourInfo": null,
        "hasBroadcastInfo": false,
        "broadcastInfo": null,
        "michelinGuide": null,
        "reservation": null,
        "hasSmartOrder": false,
        "hasNPay": false,
        "reservationLabel": {
          "preOrder": false,
          "standard": false,
          "table": false,
          "takeout": false
        },
        "contentsInfo": null,
        "ratingInfo": null,
        "reviewDisplay": [
          {
            "sid": "1789936692",
            "bodySummary": "카페무무 강원도 강릉시 원대로 39 1층 매일 10:00-22:00 포장 가능 반려동물 동반 가능 오늘 소개해드릴 곳은 강릉 교동에 위치한 카페 무무입니다~! 터미널 오거리에서 택",
            "url": "https://m.blog.naver.com/wlsfla5919/223018451759",
            "nick": "맛먹",
            "profileImg": "http://blogpfthumb.phinf.naver.net/MjAyMjExMTBfMjI0/MDAxNjY4MDcxMDYxODg0.or73H-XY7CAQsEssegIu2cZbVnPd1bLq87cRR0W1Zu4g.5GOVApUJAwOiioK7_BbYStdVd6rWyezlfOTX9y7MTskg.PNG.wlsfla5919/profileImage.png"
          },
          {
            "sid": "1789936692",
            "bodySummary": "교동에 위치한 아기자기한 카페 무무. 시그니처 캐릭터가 아주 귀엽당 ㅎㅎ 올해 4월쯤에 오픈했으니 생긴지 반년도 채 안된 신상카페! 벽 곳곳에 붙어있는 귀여운 엽서들도 인상적이다.",
            "url": "https://m.blog.naver.com/ggukyong96/222886978515",
            "nick": "용그미",
            "profileImg": "http://blogpfthumb.phinf.naver.net/MjAyMzA4MjRfMTg1/MDAxNjkyODg2OTQ3NjI2.LjjAKR9ZY_A3vSWXPIEUa2vusOLrDT0SBDBp2ShkRVkg.KpZrlCPI0lJAVpWCAHIyzGiM1rUjej0FO6j2SPuuz9Ig.JPEG.pig12052/profileImage.jpg"
          },
          {
            "sid": "1789936692",
            "bodySummary": "강릉 카페무무 주소 : 강릉시 원대로39 번호 : 010-3510-8191 영업시간 : 10:00 ~ 22:00 주차유무 : 카페 앞 도로에 주차 정말 오랜만에 남편과 함께하는 나",
            "url": "https://m.blog.naver.com/hongji1012/222729745872",
            "nick": "홍꼼",
            "profileImg": "http://blogpfthumb.phinf.naver.net/MjAyMzAyMjVfMTk3/MDAxNjc3MzE1NTQwNDU2.fWxtR9mbudz6wISedJ1Io4Esv3Ppr06-USxddVAT0LAg.oWSFt91XuQFiiT-m620ucoZK77dQKEItXFK3PFbyVdog.JPEG.hongji1012/20221217_085249_494.jpg/20221217_085249_494.jpg"
          }
        ]
      },
      {
        "rank": 2,
        "id": "1873563885",
        "name": "집밥생각",
        "x": "128.881547",
        "y": "37.7571609",
        "distance": 0.283,
        "categoryName": "한식",
        "categoryPath": [
          [
            "220036",
            "220037",
            "220053"
          ]
        ],
        "category": [
          "음식점",
          "한식"
        ],
        "reviewCount": 119,
        "averagePrice": 10000,
        "address": "강원특별자치도 강릉시 교동 1733-4 집밥생각",
        "roadAddress": "강원특별자치도 강릉시 원대로 27",
        "abbrAddress": "교동 1733-4 집밥생각",
        "shortAddress": [
          "강원 강릉시",
          "원대로 27"
        ],
        "displayContext": [],
        "labelTheme": "한식",
        "microReviews": [
          "매콤달콤 김치두루치기의 매력"
        ],
        "cardDescription": "매콤달콤 김치두루치기의 매력",
        "description": "강릉 터미널 근처 맛집 집밥생각",
        "images": [
          "https://pup-review-phinf.pstatic.net/MjAyNTA1MjhfMTMg/MDAxNzQ4NDI5NzgxNTUw.WLTita35jg_79m3afWbd-FXaE1wu9r3WDOm5che7vycg.jMkiAZLl21LQ8tvJakGYG2-dXYhC5TH7v3mvUaqtJPUg.JPEG/41E23F47-FA0F-4789-AD71-C87ABB1AA5F8.jpeg",
          "https://pup-review-phinf.pstatic.net/MjAyNTA0MDZfMTcx/MDAxNzQzOTI1NzY3MjQ4.XKbOKcSU9fEWa0K4tOYH5Zt2b6oEBrhEsyaY_ks8dcYg.zFO0MdXl-SOVWAOoACdBHT6oRjir52hfaZmuvUyWrjEg.JPEG/6CBF9449-3CA8-4A29-BAE3-C21568BFFA71.jpeg",
          "https://ldb-phinf.pstatic.net/20221118_294/1668744642908fAHfU_JPEG/KakaoTalk_20221118_130556305.jpg",
          "https://pup-review-phinf.pstatic.net/MjAyNTA1MjFfMTcz/MDAxNzQ3Nzg5MTA4ODU0.KThujHDpaDT_dwF2MQ-l428TBVFT9_3WICQC8Ln54HYg.-Ub6IrBIhJsWMnaE3fX1BcKGYac6lnLpi8ThcN_ormkg.JPEG/4F91F7F4-BED0-4A90-844F-0A37A42C8C89.jpeg",
          "https://pup-review-phinf.pstatic.net/MjAyNTA5MDFfMTAg/MDAxNzU2Njk2NzkzOTk2.poq_Pk663pcUWZYXS1fGdFy-XfG_L6rnjK6NvYu2aL8g.4IRp8fu7Gftxq9w-zruKzQ4vdQM2JmhzIzm0w_qVB0wg.JPEG/5CDA07FF-EE3E-45D2-9615-8E863A35D997.jpeg"
        ],
        "marker": "nres://marker/00079-00145",
        "markerSelected": "nres://marker/00079-00309",
        "markerId": "220053",
        "bizhourInfo": null,
        "hasBroadcastInfo": false,
        "broadcastInfo": null,
        "michelinGuide": null,
        "reservation": null,
        "hasSmartOrder": false,
        "hasNPay": false,
        "reservationLabel": {
          "preOrder": false,
          "standard": false,
          "table": false,
          "takeout": false
        },
        "contentsInfo": null,
        "ratingInfo": null,
        "reviewDisplay": [
          {
            "sid": "1873563885",
            "bodySummary": "그럴 때 정말 맛있게 먹을 수 있는 강릉맛집 집밥생각 엄마가 집에서 해준 집밥처럼 맛있고 따뜻하게 든든히 배 채운 후기! 집밥생각 강원 강릉시 원대로 27 집밥생각 033-653-",
            "url": "https://m.blog.naver.com/6111625/223300888314",
            "nick": "괠괠언니",
            "profileImg": "http://blogpfthumb.phinf.naver.net/MjAyMzAyMDZfMjg4/MDAxNjc1NjQyMzY4MjMy.21xf9QYkOWNkyJy4d2cKswMVtWcY2D2D8W8I7u0xRhog.-Z2gct9TGU2aeu8dYYrG9JGKhZ_2hhsJinxJHN9JmS4g.JPEG.6111625/profileImage.jpg"
          },
          {
            "sid": "1873563885",
            "bodySummary": "강릉시외고속터미널과는 차로 1분 거리입니다 엄마가 해주는 따뜻한 밥 집밥생각 글귀부터 벌써 따뜻하지 않나요? 강릉로컬맛집 집밥생각은 매장식사, 포장, 배달 모두 가능하답니다!! 매",
            "url": "https://m.blog.naver.com/s3222s/223294739400",
            "nick": "윤뀨",
            "profileImg": "http://blogpfthumb.phinf.naver.net/MjAyMzA1MThfMjQy/MDAxNjg0NDIwNzczOTU5.hSK2bgpo6ybPcvDq4Y5uRFfT2JHNxZuqETiu7y4q_bYg.DI5GchxuaLNg6M0TZ86IMbS5tfDHauALZ_Jx3Tgv4EQg.JPEG.s3222s/profileImage.jpg"
          },
          {
            "sid": "1873563885",
            "bodySummary": "주차는 주변 옆 골목에 주차해도 되구요 내부로 들어서면 아담하고 편안한 식당이에요 친절하신 사장님이 반갑게 맞아주시구요 돼지김치찌게 돼지김치두루치기 등등 주류 1인식사등을 판매하고",
            "url": "https://m.blog.naver.com/kerasa/223292906381",
            "nick": "해피냥냥",
            "profileImg": "http://blogpfthumb.phinf.naver.net/MjAyMjA4MTFfODcg/MDAxNjYwMjE0NzcxMjY2.9dlaY74ceW_EoquYsyvk4-H1XWv34LgTgMxnlbq9crcg.DtX60uI6qVCs1e6K9CGqtBOy8NUUDFPq5N3FiXpk0gog.JPEG.kerasa/profileImage.jpg"
          },
          {
            "sid": "1873563885",
            "bodySummary": "이번에 강릉에 있는 양떼목장을 갔는데 겸사겸사 강릉에 맛있다는 이정희 김치두루치기 집을 가기로했다. 강릉가는데 2시간 걸려서 전화하니1시30분까지 라스트 오더랬다. 두근두근한 마음",
            "url": "https://m.blog.naver.com/da_joy_/223247466846",
            "nick": "조이의 일상",
            "profileImg": "http://blogpfthumb.phinf.naver.net/MjAyMTA1MjdfMTI0/MDAxNjIyMDQxOTg3ODE3.Oe4BwWM0xjd86SDq1IQjEv_Cu3sXNZyphpjNIigodnQg.ro04oW2BTVq_ae6cJ9lI874kglxOFybtgC1v6V1RJyYg.JPEG.ek__wjd/%25EC%259E%2587%25EC%25B8%25A0%2B%25EB%25AF%25B81.jpg"
          },
          {
            "sid": "1873563885",
            "bodySummary": "강릉 버스터미널 근처 맛집 집밥생각 강원 강릉시 원대로 27 집밥생각 ⏰ 화~일 10:00~21:00 (월요일 휴무) 033-653-4141 • 주문한 메뉴 • 돼지김치 두루치기 ",
            "url": "https://m.blog.naver.com/eco178/223210395514",
            "nick": "은콩",
            "profileImg": "http://blogpfthumb.phinf.naver.net/MjAyMjAzMThfOTgg/MDAxNjQ3NTg4ODc0OTk5.yd7hmvJW7OVOnS1K1p3nkt6oX0jJe-K8KOgyLToUUyQg.ycG3t61COBqr2sSfIbsDkC3r7qxj8tIouTTMxqDyH9kg.PNG.eco178/profileImage.png"
          }
        ]
      },
      {
        "rank": 3,
        "id": "15285585",
        "name": "땡삐식당",
        "x": "128.881495",
        "y": "37.7567934",
        "distance": 0.305,
        "categoryName": "한식",
        "categoryPath": [
          [
            "220036",
            "220037",
            "220053"
          ]
        ],
        "category": [
          "음식점",
          "한식"
        ],
        "reviewCount": 59,
        "averagePrice": 30000,
        "address": "강원특별자치도 강릉시 교동 1736-1",
        "roadAddress": "강원특별자치도 강릉시 원대로 23",
        "abbrAddress": "교동 1736-1",
        "shortAddress": [
          "강원 강릉시",
          "원대로 23"
        ],
        "displayContext": [],
        "labelTheme": "부모님과 함께",
        "microReviews": [],
        "cardDescription": "강원특별자치도 강릉시 교동 1736-1",
        "description": "",
        "images": [
          "https://pup-review-phinf.pstatic.net/MjAyNTA0MDhfMjQx/MDAxNzQ0MTA2NjUzMDkz.RpMUyd_dzrhMaqdUQsSJqXy8zZa_X_QGRuzBIyOMKCIg.OdIuP_YZxCBY21P6OFONe-hNYzC2p7yq3YlH5pA3DZEg.JPEG/20250408_185115.jpg.jpg",
          "https://ldb-phinf.pstatic.net/20191226_205/1577358676013CxiLg_JPEG/6LR0dPm-b6SKQLca3tjBLQeG.jpg"
        ],
        "marker": "nres://marker/00079-00145",
        "markerSelected": "nres://marker/00079-00309",
        "markerId": "220053",
        "bizhourInfo": null,
        "hasBroadcastInfo": false,
        "broadcastInfo": null,
        "michelinGuide": null,
        "reservation": null,
        "hasSmartOrder": false,
        "hasNPay": false,
        "reservationLabel": {
          "preOrder": false,
          "standard": false,
          "table": false,
          "takeout": false
        },
        "contentsInfo": null,
        "ratingInfo": null,
        "reviewDisplay": []
      },
      {
        "rank": 4,
        "id": "15378791",
        "name": "영세감자탕",
        "x": "128.8815599",
        "y": "37.75729",
        "distance": 0.276,
        "categoryName": "감자탕",
        "categoryPath": [
          [
            "220036",
            "220037",
            "220067",
            "220681"
          ]
        ],
        "category": [
          "한식",
          "감자탕"
        ],
        "reviewCount": 31,
        "averagePrice": 7000,
        "address": "강원특별자치도 강릉시 교동 1733-5",
        "roadAddress": "강원특별자치도 강릉시 원대로 29",
        "abbrAddress": "교동 1733-5",
        "shortAddress": [
          "강원 강릉시",
          "원대로 29"
        ],
        "displayContext": [],
        "labelTheme": "착한 가격",
        "microReviews": [],
        "cardDescription": "강원특별자치도 강릉시 교동 1733-5",
        "description": "",
        "images": [
          "https://pup-review-phinf.pstatic.net/MjAyNTA1MTFfMiAg/MDAxNzQ2OTYxODA1Mjc4.f6rRHgNm9e8C_RCaQzmp4u8zZuoMUqQEgIXvFnOcZkog.mSkw42fWDVR1MXa5OZo8kQmhST5VBWWh3R5p9qQUOacg.JPEG/20250505_163313.jpg.jpg",
          "https://ldb-phinf.pstatic.net/20191226_56/1577359114874nf4tU_JPEG/XxvOJs4mHiPDkmMudkKSg_PE.jpg"
        ],
        "marker": "nres://marker/00079-00145",
        "markerSelected": "nres://marker/00079-00309",
        "markerId": "220681",
        "bizhourInfo": null,
        "hasBroadcastInfo": false,
        "broadcastInfo": null,
        "michelinGuide": null,
        "reservation": null,
        "hasSmartOrder": false,
        "hasNPay": false,
        "reservationLabel": {
          "preOrder": false,
          "standard": false,
          "table": false,
          "takeout": false
        },
        "contentsInfo": null,
        "ratingInfo": null,
        "reviewDisplay": []
      },
      {
        "rank": 5,
        "id": "13350659",
        "name": "피나치공 강릉 교동점",
        "x": "128.8815539",
        "y": "37.757185",
        "distance": 0.282,
        "categoryName": "피자",
        "categoryPath": [
          [
            "220036",
            "220044",
            "220136",
            "220974"
          ]
        ],
        "category": [
          "음식점",
          "피자"
        ],
        "reviewCount": 49,
        "averagePrice": 5000,
        "address": "강원특별자치도 강릉시 교동 1733-4",
        "roadAddress": "강원특별자치도 강릉시 원대로 27",
        "abbrAddress": "교동 1733-4",
        "shortAddress": [
          "강원 강릉시",
          "원대로 27"
        ],
        "displayContext": [],
        "labelTheme": "착한 가격",
        "microReviews": [],
        "cardDescription": "전국 약500개의 가맹점, 20년 전통의 피나치공(피자나라치킨공주) 입니다. * 가격이 저렴하다고 음식의 퀄리티가 절대 저렴하지 않습니다  ~전 메뉴 콜라 제공 ~ * M 단품,세트 - 500ml , L 단품,세트 -",
        "description": "전국 약500개의 가맹점, 20년 전통의 피나치공(피자나라치킨공주) 입니다. * 가격이 저렴하다고 음식의 퀄리티가 절대 저렴하지 않습니다  ~전 메뉴 콜라 제공 ~ * M 단품,세트 - 500ml , L 단품,세트 -",
        "images": [
          "https://ldb-phinf.pstatic.net/20250804_242/1754274213135uIEwS_JPEG/%BD%C3%BD%C4%B1%C7_%BB%F3%BD%C3%C0%CC%BA%A5%C6%AE.jpg",
          "https://ldb-phinf.pstatic.net/20250804_191/1754274191688r87tx_JPEG/%BD%C3%BD%C4%B1%C7_%BB%F3%BD%C3_%C0%CC%BA%A5%C6%AE_%BB%F3%BC%BC%C6%E4%C0%CC%C1%F6700px.jpg",
          "https://ldb-phinf.pstatic.net/20240806_131/1722929582787rfoLz_JPEG/photo_2024-08-06_16-32-28.jpg"
        ],
        "marker": "nres://marker/00079-00145",
        "markerSelected": "nres://marker/00079-00309",
        "markerId": "220974",
        "bizhourInfo": null,
        "hasBroadcastInfo": false,
        "broadcastInfo": null,
        "michelinGuide": null,
        "reservation": null,
        "hasSmartOrder": false,
        "hasNPay": false,
        "reservationLabel": {
          "preOrder": false,
          "standard": false,
          "table": false,
          "takeout": false
        },
        "contentsInfo": null,
        "ratingInfo": null,
        "reviewDisplay": []
      }
    ]
  }
}