{
  "result": {
    "meta": {
      "totalCount": 0,
      "count": 0,
      "request": {
        "offset": 0,
        "limit": 100,
        "boundary": {
          "minX": 128.88388557261578,
          "minY": 35.21949099099099,
          "maxX": 128.8894,
          "maxY": 35.223995495495494
        },
        "code": "01",
        "sortType": "RECOMMEND",
        "timeCode": "AFTERNOON",
        "searchCoord": "128.8866427863079;35.22174324324324",
        "adultCheckBean": {
          "isLogin": false,
          "isAdult": false,
          "isAdultContentAllowed": false
        },
        "hasReservation": false,
        "multilingualType": "KOREAN"
      },
      "recommendationCode": null,
      "radius": null
    },
    "list": []
  }
}