{
  "result": {
    "meta": {
      "totalCount": 16,
      "count": 16,
      "request": {
        "offset": 0,
        "limit": 100,
        "boundary": {
          "minX": 126.9666342627626,
          "minY": 37.55749099099099,
          "maxX": 126.96777083648634,
          "maxY": 37.558391891891894
        },
        "code": "01",
        "sortType": "RECOMMEND",
        "timeCode": "AFTERNOON",
        "searchCoord": "126.96720254962446;37.55794144144144",
        "adultCheckBean": {
          "isLogin": false,
          "isAdult": false,
          "isAdultContentAllowed": false
        },
        "hasReservation": false,
        "multilingualType": "KOREAN"
      },
      "recommendationCode": null,
      "radius": null
    },
    "list": [
      {
        "rank": 1,
        "id": "251432915",
        "name": "아크바 중림점",
        "x": "126.9675231",
        "y": "37.5583916",
        "distance": 0.058,
        "categoryName": "디저트",
        "categoryPath": [
          [
            "220036",
            "220052",
            "220563"
          ]
        ],
        "category": [
          "음식점",
          "카페,디저트"
        ],
        "reviewCount": 164,
        "averagePrice": 5000,
        "address": "서울특별시 중구 중림동 147-8",
        "roadAddress": "서울특별시 중구 중림로7길 10",
        "abbrAddress": "중림동 147-8",
        "shortAddress": [
          "서울 중구",
          "중림로7길 10"
        ],
        "displayContext": [],
        "labelTheme": "카페",
        "microReviews": [
          "밀크티 한 잔으로 만나는 특별한 휴식"
        ],
        "cardDescription": "밀크티 한 잔으로 만나는 특별한 휴식",
        "description": "약현성당 후문 앞에 위치하고 있으며, 한옥건물의 카페입니다. 스리랑카 청정다원에서 온 100년 전통의 아크바 홍차/허브차를 만나보세요. 국내 최초 나이트로 밀크티와 특별한 티 음료가 준비 ",
        "images": [
          "https://pup-review-phinf.pstatic.net/MjAyNTA5MTBfNzAg/MDAxNzU3NDY5OTU4NTU3.HvcKRxDZonixQqcH-PT-n4O34ZCvipeRUBNlkz15Gnsg.O5dGqO4Bt15FC_sH5BcE27iF2RWUje1mjv7bDPlpDX0g.JPEG/1000052408.jpg.jpg",
          "https://pup-review-phinf.pstatic.net/MjAyNTA3MzBfODgg/MDAxNzUzODgwNTgwNDk4.hMvZsvntL3YbDnSNv1zU6nR5K88kMCwSn-3j2a7OGncg.DSGkzxw4bk2pdcVOvKNEqczd_NbRA5Vcb_vzdi5Sl8Qg.JPEG/20250724_120059.jpg",
          "https://ldb-phinf.pstatic.net/20250710_156/1752148955815Q42ay_JPEG/1000003954.jpg",
          "https://pup-review-phinf.pstatic.net/MjAyNTEwMjBfMzcg/MDAxNzYwOTM5NDkxNjQw.dC_H3nAfnssBA8paWezDUMz4txXcwdmyM02VGt8KdOkg.a_6HqOfH0jBZS1kFgbdSEAffGiUNo8mu0JoYYVDgxu8g.JPEG/3672F9BC-3E36-46CA-BC65-7F57694D8BB3.jpeg",
          "https://ldb-phinf.pstatic.net/20250710_255/1752148955744Ph61u_JPEG/1000003952.jpg",
          "https://pup-review-phinf.pstatic.net/MjAyNTA3MjhfMjk0/MDAxNzUzNjY3MTcyODU0.sfyZtOhNT-BtwJjnQ47J-Rd0GwgJi7GokKA9oXl5Ji4g.shSRU8uZO9kUIfWg9k_YSDvXTZw_R_RPCCeSTuX7z_Eg.JPEG/20250724_122123.jpg.jpg",
          "https://ldb-phinf.pstatic.net/20190705_33/1562327505356vLPwX_JPEG/b71uzrHutSmAS2Vx3-XUtqwA.jpeg.jpg",
          "https://pup-review-phinf.pstatic.net/MjAyNTA0MDVfMjE0/MDAxNzQzODI4MzEzMDQ0.PFeNpRn0mCAG3AKTMBp0ANbyXy7vHiRl6ER2htzEmcYg.T3MuzMRm1YN-33osNF-QdvucCY3OaemAlM1YL3osNa4g.JPEG/20250404_122942.jpg.jpg",
          "https://pup-review-phinf.pstatic.net/MjAyNTA3MjZfMjUw/MDAxNzUzNTI0OTA3MzIz.yS0ig5TQKh14_O5S_1Ppd9PU5acRGlREd2e8P6YHRgog.WJ9M5FmTtPAFK0JqOJZoJSNaEmELIrmwO9cZ2P4rJVsg.JPEG/20250710_193612.jpg.jpg",
          "https://pup-review-phinf.pstatic.net/MjAyNTA2MTJfMjI4/MDAxNzQ5NjU2OTA4MzYy.wLD9b2V3BjXOKWQtibfOBtK52z67s5I6dT0a-DddzMIg.m42iWpIhgJKy6daa0alXvJBgJjth4M8FaoAV7V-XvFEg.JPEG/BC1F533C-5FD5-42D8-A569-6B984E12A193.jpeg"
        ],
        "marker": "nres://marker/00079-00145",
        "markerSelected": "nres://marker/00079-00309",
        "markerId": "220563",
        "bizhourInfo": null,
        "hasBroadcastInfo": false,
        "broadcastInfo": null,
        "michelinGuide": null,
        "reservation": null,
        "hasSmartOrder": false,
        "hasNPay": false,
        "reservationLabel": {
          "preOrder": false,
          "standard": false,
          "table": false,
          "takeout": false
        },
        "contentsInfo": null,
        "ratingInfo": null,
        "reviewDisplay": [
          {
            "sid": "251432915",
            "bodySummary": "그렇게 이 카페를 다시 찾은 것이다. 나는 익숙한게 좋다. 고요한것을 좋아한다. 이번엔 비록 손님들이 꽤 있어 전보다 좋은 감정을 느끼진 못했지만 어쨌든 사장님 입장에선 좋은거니 ",
            "url": "https://m.blog.naver.com/sgj0825/223267620204",
            "nick": "기록쟁이",
            "profileImg": "http://blogpfthumb.phinf.naver.net/MjAyMjAxMjhfMjk4/MDAxNjQzMzM3MDcxMjUz.WUxnlfrDetbZOR1xDeuFRgNuVXE1-AVVRdro6kFptKsg.PUm3MmTEHZisd0shuVwty2gFpV3MIB_3drXFWi5VKxEg.JPEG.sgj0825/profileImage.jpg"
          },
          {
            "sid": "251432915",
            "bodySummary": "밀크티가 메인이지만 홍차 등 다른 음료도 다양하게 취급하고 있으니 참고하세요- 또 밀크티의 경우 보통 카페인이 함유되어 있기 마련인데 루이보스 크림 밀크티처럼 무카페인 선택지가 있",
            "url": "https://m.blog.naver.com/kimminjoo/223067651687",
            "nick": "쭈",
            "profileImg": "http://blogpfthumb.phinf.naver.net/MjAyMzA3MDZfMTU5/MDAxNjg4NjMxNzUyMjE4.raqC1am_L-MoIpnLZNnU5lGWgCER5ASB-iKQbeDNhDUg.k6yu30WU5J3CLXwT_8lqVOhPtsUrjeh5AgN2XnQCzT4g.PNG.kimminjoo/profileImage.png"
          },
          {
            "sid": "251432915",
            "bodySummary": "서울역 뒷편 중림동 홍차 카페 아크바 중림점 입니다. 중림동 약현성당 근처에 위치해있구요 아주 오래된 주택건물이 개조된 카페였어요. 서까래까지 그대로 살려진 사장님과 함께 오랜 세",
            "url": "https://m.blog.naver.com/yonijong/222373019659",
            "nick": "퐁퐁",
            "profileImg": "http://blogpfthumb.phinf.naver.net/MjAyMjAyMDFfMTI2/MDAxNjQzNjk3MTM3ODU1.sg2tkhC7X4dYx9GmD1WJ1rFohDE4fUW4H5ko2cFScfAg.feFia7o-sJdvKM8ND7iabjjkOEpFZPl0hYcUwOxM6YMg.JPEG.yonijong/profileImage.jpg"
          },
          {
            "sid": "251432915",
            "bodySummary": "사장님이 치킨에 자부심이 있으시더라구요. 밖에 테라스도 작게 있어요. 들어가면 차 전문점이라는걸 알수있습니다. 좀 오래된 동네카페같아요. 사랑방? 세월이 느껴졌습니다. 저도 홍차는",
            "url": "https://m.blog.naver.com/hyes110/222345441581",
            "nick": "루니",
            "profileImg": "http://blogpfthumb.phinf.naver.net/MjAyNDAxMjFfMjc3/MDAxNzA1Nzc5MDgwOTMx.xf_V64KCtTq3BrVaAD9rw5-7R7jDEvfIyEm1OHrSpRYg.Tuoqj7zfyjIBRNYV1CvJOWVlbA8Mzu2TgVX_hjASrmwg.JPEG.hyes110/profileImage.jpg"
          },
          {
            "sid": "251432915",
            "bodySummary": "남아있는 서까래나 목조건물의 흔적들을 보면 리모델링 전의 외형이 약간 보이는 거 같기도ㅋㅋㅋ 사람이 살기에 더 이상 어려운 낡은 건물들은 이렇게 리모델링하는 것도 나쁘진 않은듯! ",
            "url": "https://m.blog.naver.com/songa2580/221268110021",
            "nick": "섬초",
            "profileImg": "http://blogpfthumb.phinf.naver.net/MjAyMzA1MDVfNjIg/MDAxNjgzMjEyNTQ1MTAw.kC3sSzjBe4llp5OR1x-NNKd2JSe9njDKw0XbyHXr9ygg.OG6aRmj4p9MT6q5gVW_wUidnhptSkq4C1nHklxVCuxEg.PNG.songa2580/profileImage.png"
          }
        ]
      },
      {
        "rank": 2,
        "id": "1955713566",
        "name": "바르다 김선생 중림서울로점",
        "x": "126.9675269",
        "y": "37.5576836",
        "distance": 0.041,
        "categoryName": "분식",
        "categoryPath": [
          [
            "220036",
            "220048",
            "229885"
          ]
        ],
        "category": [
          "음식점",
          "분식"
        ],
        "reviewCount": 23,
        "averagePrice": 9000,
        "address": "서울특별시 중구 중림동 325-1",
        "roadAddress": "서울특별시 중구 중림로 40",
        "abbrAddress": "중림동 325-1",
        "shortAddress": [
          "서울 중구",
          "중림로 40"
        ],
        "displayContext": [],
        "labelTheme": "착한 가격",
        "microReviews": [],
        "cardDescription": "안녕하세요. 바르다김선생 중림서울로점입니다.",
        "description": "안녕하세요. 바르다김선생 중림서울로점입니다.",
        "images": [
          "https://pup-review-phinf.pstatic.net/MjAyNTA4MTNfNzkg/MDAxNzU1MDYzMjE4ODEx.qXneg9TyDal732iVrO4dcxm-BiO3QsKX3by8WJ0yLRMg.lZPbBcGRS4gF_hbPpE4q04hxPjaB1cepLCTbq-8zG2wg.JPEG/ED105D14-5500-43C8-9D49-6533890CDB77.jpeg",
          "https://pup-review-phinf.pstatic.net/MjAyNTA1MTNfMTAy/MDAxNzQ3MDk2Njg4MTA4.33Dp-M7xe8VJqhftDEZBL8g2DRIiwWTzSnuJuz9v8S8g.uMBSfPpIJJQbCibVPIGOIiafNz7j6icBVor2K2NLUOgg.JPEG/3717D10F-E804-4507-8802-64314E22D0B9.jpeg",
          "https://ldb-phinf.pstatic.net/20180514_107/1526279778335XG5hi_JPEG/HQJ4NtG9eLYWJQXBqEndipN0.jpg",
          "https://pup-review-phinf.pstatic.net/MjAyNTEwMDRfMTA4/MDAxNzU5NTU1NTgwNzY4.2lYwV7owD4byiZ9Gb7paWBH8g-bYP-hSdmPunJn_R9Mg.nbJz6XWi902o8sBk8hHXsRatqpeiXSpRb-F2tVxwY24g.JPEG/20241120_182554.jpg.jpg",
          "https://ldb-phinf.pstatic.net/20240306_65/1709699568678CttR3_JPEG/1._%B9%D9%B8%A3%B4%D9_%B1%E8%BC%B1%BB%FD_%B7%CE%B5%E5_%C6%F7%BD%BA_%BF%B5%BB%F3%2823.06%29_01.jpg",
          "https://pup-review-phinf.pstatic.net/MjAyNTA5MDlfMjY1/MDAxNzU3NDI1MTYyNjAy.0rrTj5l-McIiSEynpkyExWLnOJbVVRIPp-vAes_3rNUg.UfRSyje7xinghMAzjQzDBWRD3dfyNRE7cA2P9bS2gXkg.JPEG/1757423726265.jpg.jpg",
          "https://ldb-phinf.pstatic.net/20240306_294/1709699549168hue5i_JPEG/2._%B9%D9%B8%A3%B4%D9_%B1%E8%BC%B1%BB%FD_%B7%CE%B5%E5_%C6%F7%BD%BA_%BF%B5%BB%F3%2823.06%29_02.jpg",
          "https://pup-review-phinf.pstatic.net/MjAyNTA1MjFfMjg3/MDAxNzQ3ODA0NTc2MTE4.4Dshrbu-B3VZPWkltxTOAZEOeL_ANpQdtjBAHqFYLjYg.BpjXrIM_TBK8JVZV0jGlkLqbWpL4w4sRADGS6wGIviog.JPEG/20250521_141534.jpg.jpg",
          "https://pup-review-phinf.pstatic.net/MjAyNTA3MDVfMTA1/MDAxNzUxNjk1ODEwNTk2.VACuBIGK_vFlkx_YsYakDfi1EFcm4XEfu0guahTRBU8g.SRLgdqwvtOls1ycbVzF0EqIY5U1gUzO79xXm128o3wsg.JPEG/33F047C6-5C8D-4EB3-BD5D-74CE07DBE787.jpeg",
          "https://pup-review-phinf.pstatic.net/MjAyNTA1MDZfMTEy/MDAxNzQ2NTA2NjA2NDY5.MrWE9JO4zDfwoQhtoClVfD9K0vkkrJ8uAgEXm9TThVYg.mGB5_PKjmPafZIsE5eYOaApzCaLgkNy0xu58yPcl52kg.JPEG/28950CE8-F170-4FF4-A5C5-760BF1062B15.jpeg"
        ],
        "marker": "nres://marker/00079-00145",
        "markerSelected": "nres://marker/00079-00309",
        "markerId": "229885",
        "bizhourInfo": null,
        "hasBroadcastInfo": false,
        "broadcastInfo": null,
        "michelinGuide": null,
        "reservation": null,
        "hasSmartOrder": false,
        "hasNPay": false,
        "reservationLabel": {
          "preOrder": false,
          "standard": false,
          "table": false,
          "takeout": false
        },
        "contentsInfo": null,
        "ratingInfo": null,
        "reviewDisplay": []
      },
      {
        "rank": 3,
        "id": "1882637825",
        "name": "남원식당",
        "x": "126.9677621",
        "y": "37.5578405",
        "distance": 0.051,
        "categoryName": "한식",
        "categoryPath": [
          [
            "220036",
            "220037",
            "220053"
          ]
        ],
        "category": [
          "음식점",
          "한식"
        ],
        "reviewCount": 101,
        "averagePrice": 0,
        "address": "서울특별시 중구 중림동 141-1 1층",
        "roadAddress": "서울특별시 중구 중림로 41",
        "abbrAddress": "중림동 141-1 1층",
        "shortAddress": [
          "서울 중구",
          "중림로 41"
        ],
        "displayContext": [],
        "labelTheme": "한식",
        "microReviews": [],
        "cardDescription": "서울특별시 중구 중림동 141-1 1층",
        "description": "",
        "images": [
          "https://ldb-phinf.pstatic.net/20190629_63/1561814142122Uml1j_JPEG/7C48azRVblpyYqVAFEwqanL8.jpeg.jpg",
          "https://ldb-phinf.pstatic.net/20190629_243/1561814134549qjOjE_JPEG/BFeOa2WpHkAfzaUpvkCbnhHC.jpeg.jpg",
          "https://ldb-phinf.pstatic.net/20190629_157/1561814148846mfmHH_JPEG/pBg0VWxt4vLVyiPsJHHHiwm3.jpeg.jpg"
        ],
        "marker": "nres://marker/00079-00145",
        "markerSelected": "nres://marker/00079-00309",
        "markerId": "220053",
        "bizhourInfo": null,
        "hasBroadcastInfo": false,
        "broadcastInfo": null,
        "michelinGuide": null,
        "reservation": null,
        "hasSmartOrder": false,
        "hasNPay": false,
        "reservationLabel": {
          "preOrder": false,
          "standard": false,
          "table": false,
          "takeout": false
        },
        "contentsInfo": null,
        "ratingInfo": null,
        "reviewDisplay": []
      },
      {
        "rank": 4,
        "id": "37724792",
        "name": "꼬모레 중림점",
        "x": "126.9673896",
        "y": "37.5577375",
        "distance": 0.028,
        "categoryName": "카페",
        "categoryPath": [
          [
            "220036",
            "220052",
            "220576",
            "221212"
          ]
        ],
        "category": [
          "카페,디저트",
          "카페"
        ],
        "reviewCount": 216,
        "averagePrice": 5000,
        "address": "서울특별시 중구 중림동 325-1",
        "roadAddress": "서울특별시 중구 중림로 40",
        "abbrAddress": "중림동 325-1",
        "shortAddress": [
          "서울 중구",
          "중림로 40"
        ],
        "displayContext": [],
        "labelTheme": "카페",
        "microReviews": [],
        "cardDescription": "서울특별시 중구 중림동 325-1",
        "description": "",
        "images": [
          "https://pup-review-phinf.pstatic.net/MjAyNTA0MDJfMTMw/MDAxNzQzNTk4OTA3NTg1.EfHM7NrpAKvTLS30EVJqNs-dcm03T1OudPFpXDyGBgQg.vUCWguMuc3JqkGWiHdy7-HFtlbVLxgtBoRc-zbABEQYg.JPEG/20250402_180619.jpg.jpg",
          "https://ldb-phinf.pstatic.net/20190626_72/156151586098328mdc_JPEG/IsHLRxTDfl2Ds6wmwjbfNLwG.jpeg.jpg"
        ],
        "marker": "nres://marker/00079-00145",
        "markerSelected": "nres://marker/00079-00309",
        "markerId": "221212",
        "bizhourInfo": null,
        "hasBroadcastInfo": false,
        "broadcastInfo": null,
        "michelinGuide": null,
        "reservation": null,
        "hasSmartOrder": false,
        "hasNPay": false,
        "reservationLabel": {
          "preOrder": false,
          "standard": false,
          "table": false,
          "takeout": false
        },
        "contentsInfo": null,
        "ratingInfo": {
          "total": "4.27",
          "receipt": null,
          "booking": null
        },
        "reviewDisplay": [
          {
            "sid": "37724792",
            "bodySummary": "'꼬모레' #꼬모레 서울 중구 중림로 40 주중 8시 ~22시 토 9시 ~19시 일 11시 ~18시 070-8848-7623 서울역 충정로역 사이에 있는 중림동에 위치한 카페입니다",
            "url": "https://m.blog.naver.com/gkshin0502/223166974094",
            "nick": "애강",
            "profileImg": "http://blogpfthumb.phinf.naver.net/MjAyMzA0MjhfMTQx/MDAxNjgyNjUwODE5MTE2.kfMSKA2TmVdBNUs_yl9glSe-3U6H7lae11EJwVMs7Ccg.b_OR4UMlypsCOmS5SaEBY-F7N9BuUwGJkXCrdw-7f-Yg.JPEG.gkshin0502/profileImage.jpg"
          },
          {
            "sid": "37724792",
            "bodySummary": "우리가 방문했을 때는 사장님과 손님 한분이 계셨고 테이블은 많지 않고 상당히 조용한 서울로에 위치한 작은 카페였다. 서울로 카페 꼬모레는 다양한 메뉴가 있었고 커피부터 시작하여 피",
            "url": "https://m.blog.naver.com/2ssungho_o/223039971111",
            "nick": "팩트Lee",
            "profileImg": "http://blogpfthumb.phinf.naver.net/MjAyMzA0MjNfNTkg/MDAxNjgyMTc5NDA3Njg5.i7t5Bws4T5Qr9DdNJgnJUBZyHrdciOPqAA0YvdaClWUg.AQ36iEjM1X3SbyMDCK0pzpdk2NaMOFGr5k2r-QwlMPwg.PNG.2ssungho_o/profileImage.png"
          },
          {
            "sid": "37724792",
            "bodySummary": "커피 앤 모어 조용하게 담소 나누기 좋은 카페 서울역/충정로역 근처 카페 꼬모레 입니다. 지난 번 레드하우스 다녀올 때 갔었던 곳인데요. 조용하고 아늑해서 잠깐 쉬어가기 좋았던 카",
            "url": "https://m.blog.naver.com/whol_/222666030405",
            "nick": "윤이나네",
            "profileImg": "http://blogpfthumb.phinf.naver.net/MjAyMTExMTVfMjQx/MDAxNjM2OTY4MjY2ODE4.XiYJ6pm7eQMxZ5VDOW8JGV3Ux2IuFZczpVXwXErR0dgg.Zg2FoAh7iLprypqNz6Tn9FrbJtAFYXi5zcK4LgoCzdYg.JPEG.whol_/profileImage.jpg"
          },
          {
            "sid": "37724792",
            "bodySummary": "꼬모레 중림점의 내부입니다. 식물들과 귀여운 강아지, 코끼리 인형이 있었어요! 인형들 덕분에 카페분위기가 더 포근하고 아기자기한 느낌이랄까요!! 테이블은 4인석으로 4개정도 있었습",
            "url": "https://m.blog.naver.com/smj6262/222570074437",
            "nick": "소소냥이",
            "profileImg": "http://blogpfthumb.phinf.naver.net/MjAyMTA3MjdfNTUg/MDAxNjI3MzQ5NzQ0NDY1.FzijyiJMGdfNZQqd1bXogIMCGB7GUH9uMNbhNEPIle8g.qnz_56idks8MvbddEp9OOuOMoxBpa9kMf-ND5D4rmiAg.PNG.smj6262/%25EC%258D%25B8%25EB%2584%25A4%25EC%259D%25BC.png"
          },
          {
            "sid": "37724792",
            "bodySummary": "충정로 카페 꼬모레 아메리카노 커피 맛집 충정로 5번출구에서 내려오다보면 아담하고 작은 카페가 있는데 남자 사장님도 친절하시네요. 충정로 카페, 꼬모레에서는 아메리카노 커피가 맛있",
            "url": "https://m.blog.naver.com/candys6017/222092896308",
            "nick": "뿌니",
            "profileImg": "http://blogpfthumb.phinf.naver.net/MjAyMjA3MjJfMzcg/MDAxNjU4NDQ2NTg3MTc1.L7m3AJGO4g_MiEbaUoYhgi9t6rEqphnYAzPbkuWuCfkg.JOfXOWNjG_2LUKxyMA7PZaqPMipYzs7jp8zFsrYAZbkg.PNG.candys6017/%25EC%25BA%25A1%25EC%25B2%2598.PNG/%25EC%25BA%25A1%25EC%25B2%2598.PNG"
          }
        ]
      },
      {
        "rank": 5,
        "id": "156600499",
        "name": "나주곰탕앤불고기",
        "x": "126.9671074",
        "y": "37.5582044",
        "distance": 0.03,
        "categoryName": "곰탕,설렁탕",
        "categoryPath": [
          [
            "220036",
            "220037",
            "220069",
            "220696"
          ]
        ],
        "category": [
          "한식",
          "곰탕,설렁탕"
        ],
        "reviewCount": 848,
        "averagePrice": 10000,
        "address": "서울특별시 중구 중림동 150-1",
        "roadAddress": "서울특별시 중구 중림로 31",
        "abbrAddress": "중림동 150-1",
        "shortAddress": [
          "서울 중구",
          "중림로 31"
        ],
        "displayContext": [],
        "labelTheme": "24시간 영업",
        "microReviews": [
          "맑은 국물로 몸보신하는 든든한 한 끼"
        ],
        "cardDescription": "맑은 국물로 몸보신하는 든든한 한 끼",
        "description": "매일 가마솥에 정성스레 끓이는 육수와 수육, 직접 반죽해서 기계로 뽑는 냉면, 동판에다가 구워 먹는 불고기. 총 90석에 1시간 무료 넓은 주차장이 있는 말근 나주곰탕입니다. 직영점으로만 운 ",
        "images": [
          "https://pup-review-phinf.pstatic.net/MjAyNTA5MjdfMzIg/MDAxNzU4OTc1MTU4NzY5.i8KZDGSjsymqCPByVRxcS65cag8Bfm9zWxHR6hcYw6Ag.ICa5mBk7HD9yDO8ci27Z-853HxyxANv7RWid2OmlNbcg.JPEG/336141A3-F65B-4C05-ABCF-85FB8A019AEA.jpeg",
          "https://pup-review-phinf.pstatic.net/MjAyNTA0MDVfMjUz/MDAxNzQzODM0NjE3MDIx.pZXcgcSDaKccCuFQsbxIB00WXXoud-VFEcKVZnbnP2Qg.EC6tPZBTQ3F7kPYIix6UwBv6L-C_sYl34XN9ER72gZgg.JPEG/20250401_114637.jpg.jpg",
          "https://ldb-phinf.pstatic.net/20190704_109/1562248304889eCYyb_JPEG/ZPhZSG_gmDJbudLiYCFsH1db.jpeg.jpg",
          "https://pup-review-phinf.pstatic.net/MjAyNTA2MDRfMjcw/MDAxNzQ5MDA4MDcxNDc0.NqTiEftqg6y0Xxp5HCzs-HvlwyTnYCYhJAoM-F_XruIg.TIaKt4c4hKuDC2udiTP1o6W1O3PyltS2oaSpFRYfjG4g.JPEG/77506BD1-0598-407A-84BC-25A479414CC9.jpeg",
          "https://pup-review-phinf.pstatic.net/MjAyNTA1MDdfNzkg/MDAxNzQ2NjEwMTQ2NDEy.ymwVCtOv2kJ82j1LyGemyFBksGr-EZbhxJ3IOqyU3aYg.h39xybKrRJpWthwyqIrM7tshRTsSDm3BhAjK0C2qmrgg.JPEG/20250506_133956.jpg.jpg",
          "https://pup-review-phinf.pstatic.net/MjAyNTA2MTFfMTU2/MDAxNzQ5NjQ2NzM5Njc1.AWi9_P5P6mByaBSKoizcaYFM0bGQUCOeqgrKIQG6K3cg.dTp0GSZ-B9L3Y6WLivdvd8MXq4_ob13PiHgHE_MQ8agg.JPEG/20250611_211210.jpg.jpg",
          "https://pup-review-phinf.pstatic.net/MjAyNTEwMDJfMSAg/MDAxNzU5NDAxMjI3MTg4.hJzehNkPaFvbUnrqMxeKQN-iLn5yeFJgxIFh37h75skg.o8Y2wGB9wrDgWJFTachK1OusD3vBAho6n3D6ea0lTgIg.JPEG/41E9B20A-51AD-45B4-B7A1-712AEF6FDC28.jpeg",
          "https://pup-review-phinf.pstatic.net/MjAyNTA3MDdfMjcg/MDAxNzUxODk2ODA2MTQw.t7VQNOdHM4fXBjfuWjLi54ytgGshobKceMWWGXRuqNwg.Sl_aFSRND_5weuw7GECSKTk3b7RTzXwLCKwfmOuDafAg.JPEG/20250707_214026.jpg.jpg",
          "https://pup-review-phinf.pstatic.net/MjAyNTA2MTlfMjE5/MDAxNzUwMzQwODM2NDUy.L3Q6xgNaU8blKDb1EO5iX5M5VOAtVX9r6-iG2VPwUk8g.TGvty0SAOWJlb1ipcpR62Q-VFte2Z14UlZ6wFvHaSNUg.JPEG/20250618_213727.jpg.jpg",
          "https://pup-review-phinf.pstatic.net/MjAyNTA5MTZfMTcx/MDAxNzU4MDMxMDgxNjYz.paHQG7fFLnHczdID4Yus08cAFmAyFIdG_KVwebCQzlMg.CbqSKA8wYklLnddIIwyqlZEr9bj9yBUQINB9wefDx1cg.JPEG/52D322D7-4CCE-451E-A021-38502CA65EB2.jpeg"
        ],
        "marker": "nres://marker/00079-00145",
        "markerSelected": "nres://marker/00079-00309",
        "markerId": "220696",
        "bizhourInfo": null,
        "hasBroadcastInfo": false,
        "broadcastInfo": null,
        "michelinGuide": null,
        "reservation": null,
        "hasSmartOrder": false,
        "hasNPay": false,
        "reservationLabel": {
          "preOrder": false,
          "standard": false,
          "table": false,
          "takeout": false
        },
        "contentsInfo": null,
        "ratingInfo": null,
        "reviewDisplay": [
          {
            "sid": "156600499",
            "bodySummary": "점심에 방문하기 좋은 말근 나주곰탕 중림점을 다녀왔습니다. 상호명이 나주곰탕인줄알았는데 네이버에 검색해보니 정확하게는 더 길더라구요 :)말근 나주곰탕 중림점 매일 00:00-24:",
            "url": "https://m.blog.naver.com/iconiciconixx/223396982361",
            "nick": "초록초록록",
            "profileImg": "http://blogpfthumb.phinf.naver.net/MjAyNDAzMDJfMTkz/MDAxNzA5MzU3MDM0OTgw.DEQCYjxrz5dSQqCBZ-RHlX4VK5O9AFc1MwE2oJNof78g.O1bq58oYQ02QQSy94LvZIAAgN24wN_KfkE3T-Ib_xAgg.JPEG/profileImage.jpg"
          },
          {
            "sid": "156600499",
            "bodySummary": "말근 나주곰탕 중림점 서울시 중구 중림로31 서울역, 충정로역 연중무휴 24시간 00:00~24:00 0507-1370-8266 올만에 반가운 지인들과 저녁을 했다. 여태까지 나주",
            "url": "https://m.blog.naver.com/zike10/223115429197",
            "nick": "놀면 뭐혀니",
            "profileImg": "http://blogpfthumb.phinf.naver.net/MjAyMzA0MjhfNjIg/MDAxNjgyNjM2Mjk2NDk5.cb10RcBK163PiXbYT9lW4BxrG7kq85Krv6cTDSYt7nEg.3D9dV9XEWo6BBZxTVjcLzqqnUHLsShPww4rg6DKWueEg.JPEG.zike10/profileImage.jpg"
          },
          {
            "sid": "156600499",
            "bodySummary": "식당 내부에는 좌식도 있어요 후배가 시킨 #나주곰탕 제가 주문한 #얼큰곰탕 고기도 많이 들어있고, 엄청 부드러워요 나주곰탕<<<<얼큰 곰탕 방문차량 주차는 1시간 무료라고 합니다 ",
            "url": "https://m.blog.naver.com/hyunnnnnny_/223033608153",
            "nick": "이대리",
            "profileImg": "http://blogpfthumb.phinf.naver.net/MjAyMzAxMjdfMSAg/MDAxNjc0ODI0ODExMjcy.gLZ1ycYt9GP7x0JM9sEQMPcz-sypdQ0Br_f8V-Rvglgg.69UOyE3trMxem6prIjF8iy3pVfpwvzibCcYkR9Le-0Ig.PNG.cg032/profileImage.png"
          },
          {
            "sid": "156600499",
            "bodySummary": "바로 충정로에서 좀 더 가까운 말근나주곰탕 집 위치도 좋고 넓기도하고 맛도 좋아서 주변 사람들에게도 자주 추천하는 곳!이랍니당 위치는 충정로역에서 삼성 아파트 사잇길로 쭉 내려오는",
            "url": "https://m.blog.naver.com/19976415/222944269368",
            "nick": "포아앙",
            "profileImg": "http://blogpfthumb.phinf.naver.net/MjAyNDAxMTBfMTkx/MDAxNzA0ODc0NjkwOTI2.JXZLOW0OBeaQE5xo6YGN9jmWUbl7Mzy-CcBHjnu8sswg.ZtcM3DI3ECUbN1d63nMRRDO89WhlWTjcBX3xZXBlYW4g.JPEG.19976415/profileImage.jpg"
          },
          {
            "sid": "156600499",
            "bodySummary": "불고기전골이 땡겨 들어갔다 사실은 갈비찜도 땡겼는데 불고기 전골을 먹기로 함 불고기 전골만 먹으면 아쉬우니까 물냉면도 시켰다 내부는 매우 넓고 깔끔하고 음식이 다 평타는 칠 것 같",
            "url": "https://m.blog.naver.com/jiyoungm90/222933797409",
            "nick": "루",
            "profileImg": "http://blogpfthumb.phinf.naver.net/MjAyMDExMzBfMzEg/MDAxNjA2NzA3NjM5OTgw.36PFUIpFqe60ZtjbWINeTF6-WC3TbIH_eQmrq-KG_7Mg.1FJpM6TQOFL1Y1vqyGGI8N728PWylt9CFfbeWddyY58g.PNG.jiyoungm90/profileImage.png"
          }
        ]
      },
      {
        "rank": 6,
        "id": "1456117091",
        "name": "즐거운생활1-1",
        "x": "126.9674883",
        "y": "37.5579546",
        "distance": 0.025,
        "categoryName": "한식",
        "categoryPath": [
          [
            "220036",
            "220037",
            "220053"
          ]
        ],
        "category": [
          "음식점",
          "한식"
        ],
        "reviewCount": 58,
        "averagePrice": 7000,
        "address": "서울특별시 중구 중림동 144-2",
        "roadAddress": "서울특별시 중구 중림로 37",
        "abbrAddress": "중림동 144-2",
        "shortAddress": [
          "서울 중구",
          "중림로 37"
        ],
        "displayContext": [],
        "labelTheme": "착한 가격",
        "microReviews": [],
        "cardDescription": "서울특별시 중구 중림동 144-2",
        "description": "",
        "images": [
          "https://ldb-phinf.pstatic.net/20191107_258/1573096628593v4k0p_JPEG/UBA7Jg-ynVUFMyd2FIsXEa-l.jpeg.jpg",
          "https://ldb-phinf.pstatic.net/20200611_81/1591849930700Ng9Tk_JPEG/yzbCInKMz1RR-bT6y8bLaarb.jpg"
        ],
        "marker": "nres://marker/00079-00145",
        "markerSelected": "nres://marker/00079-00309",
        "markerId": "220053",
        "bizhourInfo": null,
        "hasBroadcastInfo": false,
        "broadcastInfo": null,
        "michelinGuide": null,
        "reservation": null,
        "hasSmartOrder": false,
        "hasNPay": false,
        "reservationLabel": {
          "preOrder": false,
          "standard": false,
          "table": false,
          "takeout": false
        },
        "contentsInfo": null,
        "ratingInfo": null,
        "reviewDisplay": []
      },
      {
        "rank": 7,
        "id": "1414698374",
        "name": "명동칼국수 중림동점",
        "x": "126.9677417",
        "y": "37.5575792",
        "distance": 0.062,
        "categoryName": "칼국수,만두",
        "categoryPath": [
          [
            "220036",
            "220037",
            "220073",
            "220718"
          ]
        ],
        "category": [
          "한식",
          "칼국수,만두"
        ],
        "reviewCount": 615,
        "averagePrice": 9000,
        "address": "서울특별시 중구 중림동 327-1",
        "roadAddress": "서울특별시 중구 중림로 42",
        "abbrAddress": "중림동 327-1",
        "shortAddress": [
          "서울 중구",
          "중림로 42"
        ],
        "displayContext": [],
        "labelTheme": "착한 가격",
        "microReviews": [],
        "cardDescription": "서울특별시 중구 중림동 327-1",
        "description": "",
        "images": [
          "https://pup-review-phinf.pstatic.net/MjAyNTA1MjZfNjQg/MDAxNzQ4MjMxMTI1MTQ2.mrC9oBx_BhkOmYN-xiKqxNi8EhMMmtvL4BdIGmp5fwEg.mEvRwosoZ8cOC5_pQApsPl6hsThpmldyOu4aVhh-eAkg.JPEG/996DAFA9-CE7F-426E-8D30-039D14CE28A9.jpeg",
          "https://pup-review-phinf.pstatic.net/MjAyNTA4MzFfMjA0/MDAxNzU2NTcxMjgyODY4.AagDts3P7s6a-obHg22dv5sYrJe2dJsU7m3NzOXze4kg.gl6xYmZp5YbEtJN_gljYzNuex9tPYaSStqYX8gNSG0gg.JPEG/AB7D8FD4-CDB2-4626-9F0A-7E2856BB9811.jpeg",
          "https://ldb-phinf.pstatic.net/20190625_178/1561417381479KgrAo_JPEG/j3hAeTPu63oc6ShJMtqgaGFp.jpeg.jpg",
          "https://pup-review-phinf.pstatic.net/MjAyNTA3MjFfMTU3/MDAxNzUzMDU5NDcwODg5.3nRtpsl-SRpzD0pRtextfJUIsL7CJqVRXwZkIJa-7Wwg.aGnMGv5-ZlyU_9Az5RJeVpRfrGmTMw8BqdkyTi-WaAAg.JPEG/763A7B6B-8760-4F07-924C-938C3BE508DA.jpeg",
          "https://ldb-phinf.pstatic.net/20190628_152/15617057195164rxrH_JPEG/Hdm7E-z0UcK_KU2-6lYPp9eW.jpeg.jpg",
          "https://pup-review-phinf.pstatic.net/MjAyNTA5MDdfMjA0/MDAxNzU3MjI1Mzk1NDM3.7sPaDyiGDxz9u9yt4W9dKKlJ800PUc65359pDOTInUcg.7PU4b1Yi0UAvqkoInVkqGvq20JbqAhu60BCklHdwy0Mg.JPEG/IMG_1470.jpeg",
          "https://pup-review-phinf.pstatic.net/MjAyNTA0MTNfNjMg/MDAxNzQ0NTE4NTkyMTE1.SPbibR2SXaiAK6DutrvC8aMQq4MaaqSJ9usfhEZFJLcg.tvNbYwnk6Exyn8c9ASmgtoNQ1EhFQFJw_GMWW6RneEgg.JPEG/54331FE6-084A-4D0E-B014-3C1B6AC78C9D.jpeg",
          "https://pup-review-phinf.pstatic.net/MjAyNTA0MTFfNCAg/MDAxNzQ0MzY2NjE1NTYx.pEMXmiyc1iPisWOyv81GwMjdXMB1VK8tvy9T9pR8V_gg.L2RvxJ7vPxmbe1yMReJDDVMJFFtQBizKqsyP3VlSyWQg.JPEG/CAABD1CC-91FB-4E71-A492-E54E621156EF.jpeg",
          "https://pup-review-phinf.pstatic.net/MjAyNTA5MzBfNCAg/MDAxNzU5MTkzNzk4MzMy.ibbd9BZ2pizN75a7LbBrEKvfpLxWLggRNUPUgr8y5g4g.bvXkO8rCKd4NJ9xRN5MzfjtFrGgGinxeYE23EWTur10g.JPEG/20250515_222108.jpg.jpg",
          "https://pup-review-phinf.pstatic.net/MjAyNTA3MTdfODEg/MDAxNzUyNzMxMjIyOTU2.uweZNHsssOlNfSqPPy5qoEOB6MUnYY-7-zJ1UQxzPrwg.uEWWrGPsmGuvmJzI6DNlepjBT_zwgvb5A310dD3cbA8g.JPEG/20250515_222108.jpg.jpg"
        ],
        "marker": "nres://marker/00079-00145",
        "markerSelected": "nres://marker/00079-00309",
        "markerId": "220718",
        "bizhourInfo": null,
        "hasBroadcastInfo": false,
        "broadcastInfo": null,
        "michelinGuide": null,
        "reservation": null,
        "hasSmartOrder": false,
        "hasNPay": false,
        "reservationLabel": {
          "preOrder": false,
          "standard": false,
          "table": false,
          "takeout": false
        },
        "contentsInfo": null,
        "ratingInfo": null,
        "reviewDisplay": [
          {
            "sid": "1414698374",
            "bodySummary": "기본으로 보리차가 나오네요(따뜻X) 그리고 배추김치, 열무김치통을 가져다 주셨습니다 아, 김치 맛있더라구요 테이블마다 항아리 안에 집게가 세팅되어 있어서 집게로 김치를 먹을만큼만 ",
            "url": "https://m.blog.naver.com/slowbutsteady_haring/223363303824",
            "nick": "느꾸하링",
            "profileImg": "http://blogpfthumb.phinf.naver.net/MjAyNDAxMjlfMTQ4/MDAxNzA2NTMzMjg3MTk1.hAUfFQEanFvLeK3eHaeS19imSUrYeN141OqBVn2bv9Ag.B2lD0NsVa0Q4vIQXGQmqLIbzBABhNBJGGApZOaVprfwg.JPEG.jang_ha_ri/profileImage.jpg"
          },
          {
            "sid": "1414698374",
            "bodySummary": "해서 조금 출출하고 해서리 주변에 몰 먹을까 하다가 발견한 명.동.칼.국.수 근데 명동에 있는 오리지랄 명동칼국수랑은 전혀 다른 집입니다. 이곳 주변에 잔치 국수 등등도 많이 있었",
            "url": "https://m.blog.naver.com/kingpaik2/223342786461",
            "nick": "하쿠부장",
            "profileImg": "http://blogpfthumb.phinf.naver.net/MjAyMzA2MjhfMjI4/MDAxNjg3OTU3NzUyMzE2.i4We-yzC9pOngENHODgIOYod_iP_9qUnU7uTW6bYBt4g.F4OWYwTN3HJCEYk3a0VinIe2pl62OG2NXxbNXu0SKXkg.JPEG.kingpaik2/profileImage.jpg"
          },
          {
            "sid": "1414698374",
            "bodySummary": "찾아보니까 체인점이 엄청 많던데 이름이랑, 스타일만 비슷하고 다 다른곳이더라구요 충정로 2호선 5번출구 도보 10분 서울역 뒷편 중림동 방향으로 도보 10분 주차 불가 자체주차장은",
            "url": "https://m.blog.naver.com/hileesso/223291836145",
            "nick": "리쏘",
            "profileImg": "http://blogpfthumb.phinf.naver.net/MjAyMzExMDFfNzAg/MDAxNjk4ODQ2OTE0NjUy.COGm9o48FcPeFt5ld8io47daaNwYxCvRSPDAZ1Bdr9cg.k2gHtk4k5TSrDfEpn8l4mPlmiZKy9ina1JV6XNL6A-4g.PNG.naramar/%25EB%2584%25A4%25EC%259D%25B4%25EB%25B2%2584%25ED%2594%2584%25EC%2582%25AC.png/%25EB%2584%25A4%25EC%259D%25B4%25EB%25B2%2584%25ED%2594%2584%25EC%2582%25AC.png"
          },
          {
            "sid": "1414698374",
            "bodySummary": "'명동칼국수 중림동점' 주소 : 서울 중구 중림로 42 영업시간 : 10:00~22:00 연락처 : 02-365-1771 평일/주말 모두 영업, 주차 불가 충정로역과 서울역 중간에",
            "url": "https://m.blog.naver.com/bofb49/223268303259",
            "nick": "파파카",
            "profileImg": "http://blogpfthumb.phinf.naver.net/MjAyMjA2MDVfMTQz/MDAxNjU0NDEyODIzNjE2.PyebyzTDqvv5BIpeCfGmtPpJZ1Z9FdDbZVdOldr6Nfkg.jY6YnWaTrPfW-Y2O7qIWm8VjTQrtk4jkkcN_INUM4pIg.PNG.bofb49/%25ED%258C%258C%25ED%258C%258C%25EC%25B9%25B43.png/%25E1%2584%2591%25E1%2585%25A1%25E1%2584%2591%25E1%2585%25A1%25E1%2584%258F%25E1%2585%25A13.png"
          },
          {
            "sid": "1414698374",
            "bodySummary": "혼밥 가능 영업시간 매일 10:00 ~ 22:00 메뉴판 저는 만두칼국수 주문했어요! 여름이라 콩국수 주문하시는분 많더라고요 추천 추천 주문하면 테이블하나당 갖다주시는 김치통 김치",
            "url": "https://m.blog.naver.com/summer_0808/223140994019",
            "nick": "쨔니",
            "profileImg": "http://blogpfthumb.phinf.naver.net/MjAyMzAzMDNfMTIx/MDAxNjc3NzczMzg1Mjk1.PtMwSzdTF4V0qDTZIIr6ZKyRxKYOqoYE2NYkycNNgowg.mXb6kfmU0WDZYywt7Ir6w_1pLRWDfWjlUJXDW4hucssg.PNG.sping8486/profileImage.png"
          }
        ]
      },
      {
        "rank": 8,
        "id": "1087975802",
        "name": "륭륭활어",
        "x": "126.9673993",
        "y": "37.557689",
        "distance": 0.033,
        "categoryName": "해물,생선요리",
        "categoryPath": [
          [
            "220036",
            "220037",
            "220076",
            "220777"
          ]
        ],
        "category": [
          "한식",
          "해물,생선요리"
        ],
        "reviewCount": 0,
        "averagePrice": 0,
        "address": "서울특별시 중구 중림동 325-1 1층 103호",
        "roadAddress": "서울특별시 중구 중림로 40",
        "abbrAddress": "중림동 325-1 1층 103호",
        "shortAddress": [
          "서울 중구",
          "중림로 40"
        ],
        "displayContext": [],
        "labelTheme": "한식",
        "microReviews": [],
        "cardDescription": "서울특별시 중구 중림동 325-1 1층 103호",
        "description": "",
        "images": [],
        "marker": "nres://marker/00079-00145",
        "markerSelected": "nres://marker/00079-00309",
        "markerId": "220777",
        "bizhourInfo": null,
        "hasBroadcastInfo": false,
        "broadcastInfo": null,
        "michelinGuide": null,
        "reservation": null,
        "hasSmartOrder": false,
        "hasNPay": false,
        "reservationLabel": {
          "preOrder": false,
          "standard": false,
          "table": false,
          "takeout": false
        },
        "contentsInfo": null,
        "ratingInfo": null,
        "reviewDisplay": []
      },
      {
        "rank": 9,
        "id": "2005935572",
        "name": "도라무통 즉석떡볶이 중림점",
        "x": "126.9672952",
        "y": "37.5578251",
        "distance": 0.015,
        "categoryName": "떡볶이",
        "categoryPath": [
          [
            "220036",
            "220048",
            "220187"
          ]
        ],
        "category": [
          "분식",
          "떡볶이"
        ],
        "reviewCount": 40,
        "averagePrice": 5000,
        "address": "서울특별시 중구 중림동 324-1 1층",
        "roadAddress": "서울특별시 중구 중림로 38",
        "abbrAddress": "중림동 324-1 1층",
        "shortAddress": [
          "서울 중구",
          "중림로 38"
        ],
        "displayContext": [],
        "labelTheme": "착한 가격",
        "microReviews": [],
        "cardDescription": "즉석떡볶이 최강자 도라무통 즉석떡볶이 입니다 매콤달콤 추억의 그맛 즉석떡볶이 도라무통입니다",
        "description": "즉석떡볶이 최강자 도라무통 즉석떡볶이 입니다 매콤달콤 추억의 그맛 즉석떡볶이 도라무통입니다",
        "images": [
          "https://pup-review-phinf.pstatic.net/MjAyNTA5MjlfMTE5/MDAxNzU5MTIwMzIyNDQx.F3r5xd4nZTNCV8W8FbZx8wrAO8CCO5Bxz_oIjUDQGZMg.XKcY-X5sX98WGJJoGCYQ1W-xaFXSTxfEpdp6vPOwjsEg.JPEG/B0880DE5-F5A7-46D6-BB09-FDC7684722C0.jpeg",
          "https://pup-review-phinf.pstatic.net/MjAyNTA5MTNfNzMg/MDAxNzU3NzU2MjU4MTA5.y_gGRBL13yHLhmS0pnu5IxrbcKHtrT39umUKsVf2Fwkg.Kr0Ib88XJPi-cF6qgaEpMGmtG11aJko9JzcxXY9K5UAg.JPEG/11368E50-2867-4532-BFD2-C45A4AE95CE9.jpeg",
          "https://ldb-phinf.pstatic.net/20250629_60/1751202076919ee58q_JPEG/1000052867.jpg",
          "https://pup-review-phinf.pstatic.net/MjAyNTEwMTlfNTEg/MDAxNzYwODQ3NjYzNjA0.q_jOHYHAJWcJlut81vYY4pn8mbmknpHc3JpNCtz6yuUg.T1YRaMrjs6qW9jx3NEp332bMwK5J3gxZjIAdn9AKF-Ag.JPEG/798DD61B-9CAB-486D-AD48-4FF142BAFC53.jpeg",
          "https://ldb-phinf.pstatic.net/20250629_103/1751202076982eTtoz_JPEG/1000052928.jpg",
          "https://pup-review-phinf.pstatic.net/MjAyNTEwMTVfNjQg/MDAxNzYwNTIxMDgyODY0.SUu3hW5g8a18gGSaIqsWx7o-MTVH5HSB48CbU3FuK2gg.5KRdQmXdcBwGCGNMo2_VwBbxerNvm7c8DhYqKVhGRqgg.JPEG/20251015_182159.jpg.jpg",
          "https://ldb-phinf.pstatic.net/20250629_72/17512020770493fqn5_JPEG/1000052926.jpg",
          "https://pup-review-phinf.pstatic.net/MjAyNTA5MDZfOCAg/MDAxNzU3MTQ5NDg2NDc0.ZVMt9pd_q-DCn4jYNBp9R3-9Ws8WTlICtrO4BUx_rOIg.Amc3zeBZhIGaJs8j3Pfdxt0bP3ovKg7BAcJjgQuGXgcg.JPEG/83527753-E7D2-4525-9C3C-FB52C3F807C2.jpeg",
          "https://pup-review-phinf.pstatic.net/MjAyNTEwMTlfMTk1/MDAxNzYwODU1NTIyNzYz.12oc7GdbmTNTgLgWIJ3GQHN9Y9ioYMJKppi6Gx9BBjIg.n57vdhjFRxx23y0AQOGnDSoNvoM2Rz_-oBjABELLTBcg.JPEG/20251019_144507.jpg.jpg",
          "https://pup-review-phinf.pstatic.net/MjAyNTA5MTVfOTAg/MDAxNzU3OTA3NDQ5MjY0.HLQTi3KMeLKjOXOtnSjwHIXjrybP1XJ1TUYjRGMs09Ag.z2lwobKwQZyLsQYEmNVcoc_siLSs_IljOBuhkJa2gwYg.JPEG/20250915_123505.jpg.jpg"
        ],
        "marker": "nres://marker/00079-00145",
        "markerSelected": "nres://marker/00079-00309",
        "markerId": "220187",
        "bizhourInfo": null,
        "hasBroadcastInfo": false,
        "broadcastInfo": null,
        "michelinGuide": null,
        "reservation": null,
        "hasSmartOrder": false,
        "hasNPay": false,
        "reservationLabel": {
          "preOrder": false,
          "standard": false,
          "table": false,
          "takeout": false
        },
        "contentsInfo": null,
        "ratingInfo": null,
        "reviewDisplay": []
      },
      {
        "rank": 10,
        "id": "37868348",
        "name": "도마 중림동점",
        "x": "126.9671832",
        "y": "37.5581618",
        "distance": 0.025,
        "categoryName": "한식",
        "categoryPath": [
          [
            "220036",
            "220037",
            "220053"
          ]
        ],
        "category": [
          "음식점",
          "한식"
        ],
        "reviewCount": 2642,
        "averagePrice": 10000,
        "address": "서울특별시 중구 중림동 150-1 이화빌딩",
        "roadAddress": "서울특별시 중구 중림로 31",
        "abbrAddress": "중림동 150-1 이화빌딩",
        "shortAddress": [
          "서울 중구",
          "중림로 31"
        ],
        "displayContext": [
          "양념게장",
          "고기집",
          "냉면",
          "점심특선",
          "데이트"
        ],
        "labelTheme": "부모님과 함께",
        "microReviews": [
          "마약된장찌개와 함께하는 풍성한 한상"
        ],
        "cardDescription": "마약된장찌개와 함께하는 풍성한 한상",
        "description": "맛을 찾다 사람을 만나고, 사람이 좋아 밥상을 내놓습니다.  안녕하세요. 도마의 두 번째 걸음, 도마 중림동점입니다.  @@ 도마를 사랑해 주시는 고객님께 드리는 특별 소식 @@  좋은소금을 먹는 ",
        "images": [
          "https://pup-review-phinf.pstatic.net/MjAyNTA5MTJfMjYg/MDAxNzU3Njc0MTUwNDU3.V1qDY7FoRgYLH_VoDgu9wrAwby-aT2kxqnZCAT0xVmYg.cl9WAdZlCgOUuUglxXUjBWA0TPQhAr8yRuS4qWzzxmAg.JPEG/80AFCACD-14BD-4E71-BC3B-9C2B29AE6CDD.jpeg",
          "https://pup-review-phinf.pstatic.net/MjAyNTEwMjVfMjEw/MDAxNzYxMzgyNzE0NTUy.j3i9wa6S2J7ieet7lfVxgdhMDAl8HGt21fRXS8Yc7oog.MFrETl7YiLtsDV6FLP7vkzn-Zhm0eeeFXOu12tb0xFYg.JPEG/20251025_175614.jpg.jpg",
          "https://ldb-phinf.pstatic.net/20241219_73/1734600395328ykEW5_JPEG/DSC04074.jpg",
          "https://pup-review-phinf.pstatic.net/MjAyNTEwMDdfMTc5/MDAxNzU5ODMzNDUwMTU3.UBs4gEUbzf5LROp9-z8x6NQm-0p9jT6urI_zk05qmA8g._FMiDM1i0v3Abl-uApJwPx9dj4DeydIDnAr5A8CW27Eg.JPEG/A781C98B-58CE-40A1-B423-C4C3E8F7645A.jpeg",
          "https://ldb-phinf.pstatic.net/20241219_82/1734600395193lIv8M_JPEG/DSC03549.jpg",
          "https://pup-review-phinf.pstatic.net/MjAyNTEwMTFfMTc3/MDAxNzYwMTgwMDEyNzM4.kxMYLbyI_ruF8fmjwtUn8bFDaiygLTPbxEhYyIlbGagg.51U2XT3BK2fzb8Ld2jYH6WANmaoVe0sVMN6UYNg4oAMg.JPEG/20251011_191835.jpg.jpg",
          "https://ldb-phinf.pstatic.net/20241219_198/1734599901268rUWIX_JPEG/DSC04207.jpg",
          "https://pup-review-phinf.pstatic.net/MjAyNTA1MjFfMjc0/MDAxNzQ3ODIyMTUzOTMz.v_86pfwy9P4ItleoHbxZBMrIFwdLu6t9BIXh9zWEkUwg.nvgWM9DPz8psonoz50inAJqOkRK3lau8TNEs5cU99zwg.JPEG/20250521_174326-1747817014762.jpg",
          "https://pup-review-phinf.pstatic.net/MjAyNTEwMThfNTgg/MDAxNzYwNzgwMTM2NTM1.4WQ_w9er_O7zwqVEtaxQbQW0ArkMA4-QXS6EmVh16_gg.v0ZeCmb-gc0CW4mtJmTRZmvUpRMCd0xKp5BfCZxvf7sg.JPEG/20251018_183341.jpg.jpg",
          "https://pup-review-phinf.pstatic.net/MjAyNTA1MDZfNTgg/MDAxNzQ2NTI3MDMyODE3.2frMZvihDWaljND4p0frlVnqF0WJpc8nE-H-ef1iCjEg.N8-kQZmo0RLNqcp9wLQhM63JiRI2BLjZROKC3HHJyssg.JPEG/CE8521F1-1C0E-4357-8D35-197A8203006B.jpeg"
        ],
        "marker": "nres://marker/00079-00145",
        "markerSelected": "nres://marker/00079-00309",
        "markerId": "220053",
        "bizhourInfo": null,
        "hasBroadcastInfo": false,
        "broadcastInfo": null,
        "michelinGuide": null,
        "reservation": null,
        "hasSmartOrder": false,
        "hasNPay": true,
        "reservationLabel": {
          "preOrder": false,
          "standard": true,
          "table": false,
          "takeout": false
        },
        "contentsInfo": null,
        "ratingInfo": null,
        "reviewDisplay": [
          {
            "sid": "37868348",
            "bodySummary": "소고기라 가격이 좀 있는 편이에요. 그래도 부위가 다 맛있는 부위에 모듬으로 주문하면 여러 부위를 한번에 맛볼수도 있습니다. 기본 반찬이 나왔구요. 양념 게장도 주십니다. 숯불이 ",
            "url": "https://m.blog.naver.com/ul_227/223398033680",
            "nick": "눌눌",
            "profileImg": "http://blogpfthumb.phinf.naver.net/MjAyMjA2MjlfMjk5/MDAxNjU2NDg1MzAwMjQx.sU4zAcsT4WTscp1GSal96ygfOiccoWw4fARbrqW5oXEg.z8Zg4IiWyMTvysa4KhaCXNe04ws8T4MYJ1Y0OLZFo4Ag.PNG.ajskgh/profileImage.png"
          },
          {
            "sid": "37868348",
            "bodySummary": "도마 중림동점 서울 중구 중림로 31 이화빌딩 이번에 부모님 생신이셔서 맛있는 식사 사드리고 싶어서 서울역 맛집 찾아보다가 도마 중림동점 추천 받아 다녀왔어요 ㅎㅎ 서울역 맛집 도",
            "url": "https://m.blog.naver.com/b__0805/223379193600",
            "nick": "채채맘",
            "profileImg": "http://blogpfthumb.phinf.naver.net/MjAyMzAyMTZfMTc0/MDAxNjc2NTU3NzU2MDQ2.BlmsUHrfjnVF3XlKyJhzta6mF1fSuP3vJsNSSMI5h7Qg.OvYMzBcJOeBQRFyX9bYwEk81XeULTY8qa5PnKah85SAg.PNG.b__11299/photo2672685.png"
          },
          {
            "sid": "37868348",
            "bodySummary": "주차하고 1층으로 올라오면 딱 보이는 도마! 주문메뉴 도마모듬B - 29,000원 마약된장찌개 - 8,000원 물냉면 - 8,000원 맛있는 밥 - 1,000원 서울역 맛집 도마의",
            "url": "https://m.blog.naver.com/kk_garam/223370499570",
            "nick": "람로그",
            "profileImg": "http://blogpfthumb.phinf.naver.net/MjAyMzAxMTdfNjYg/MDAxNjczOTU5MDU4Mzc4.ReJxlmlqDz1vKRyCQ892J4sdy_ljANsfYC2s9X1FtEgg.LTs6JpNCSJ0dqa99DJELi95hZ4iziJtJUXB494xuLSQg.PNG.kk_garam/profileImage.png"
          },
          {
            "sid": "37868348",
            "bodySummary": "이번엔 도마입니다 ㅎㅎ 조금만 늦으면 대기를 해야하는 직장인들의 슬픔 ㅜㅜ 고기 맛집이라는 도마에서 점심엔 솥밥정식을 판매하더라구요. 그래서 고등어 솥밥 정식과 제육 정식, 제육 ",
            "url": "https://m.blog.naver.com/un_heee/223370166050",
            "nick": "어니모닝",
            "profileImg": "http://blogpfthumb.phinf.naver.net/MjAyMjA2MjFfMTUz/MDAxNjU1ODAzMjkyMDAx.5mIadvHv3eGy4-2Weo6lCwg8km6HWUh9l43BpNjfGGMg.OstZFRhZVVXZawUf9ckUfU_8L-LEz1UWVfejbG0b2dIg.PNG.un_heee/profileImage.png"
          },
          {
            "sid": "37868348",
            "bodySummary": "중림동 맛집 도마 중림동점 고기 아니더라도 한식을 드실수있는 정식 메뉴들도 다양하게 판매하고있으니 제육볶음,고등어,육회비빔밥 좋아하시는분들은 점심 식사하시러 방문하기에도 괜찮을것 ",
            "url": "https://m.blog.naver.com/k__0805/223364513397",
            "nick": "개애맘",
            "profileImg": "http://blogpfthumb.phinf.naver.net/MjAyMjEyMzBfMjcz/MDAxNjcyNDA5MTAyMjUx.A9GJArGp4QWgjmMML3TR1xGPhqcyTgRUr3AL9r6GFtcg.1gMYdIRBTuEi_xQuXXG95TvKe-sz7frTTvw8VnmO9PIg.PNG.k__0805/profileImage.png"
          }
        ]
      },
      {
        "rank": 11,
        "id": "2060060309",
        "name": "제비한옥",
        "x": "126.96759",
        "y": "37.5582136",
        "distance": 0.046,
        "categoryName": "한식",
        "categoryPath": [
          [
            "220036",
            "220037",
            "220053"
          ]
        ],
        "category": [
          "음식점",
          "한식"
        ],
        "reviewCount": 66,
        "averagePrice": 10000,
        "address": "서울특별시 중구 중림동 147-5 1층",
        "roadAddress": "서울특별시 중구 중림로7길 6",
        "abbrAddress": "중림동 147-5 1층",
        "shortAddress": [
          "서울 중구",
          "중림로7길 6"
        ],
        "displayContext": [],
        "labelTheme": "한식",
        "microReviews": [
          "전통 한옥의 정취 속 녹두전의 고소함"
        ],
        "cardDescription": "전통 한옥의 정취 속 녹두전의 고소함",
        "description": "제비가 봄과 함께 찾아와 복을 전하듯, 정성스레 준비한 음식으로 찾아주시는 모든 분께 행복을 전합니다. 제비한옥에서 준비하는 매 끼니가 여러분의 하루에 좋은 기운을 드리기를 바랍니다.",
        "images": [
          "https://pup-review-phinf.pstatic.net/MjAyNTA0MjZfMjAg/MDAxNzQ1NjY2ODk3NDA1.VOkuzcuDEmVJsUU8ly1lhhIgE1Lza6_Z2YdthEj5uggg.z43elnVUOBvETgX0l6X-BSYKynMnwr-he5hd_Seqcycg.JPEG/20250426_180406.jpg",
          "https://pup-review-phinf.pstatic.net/MjAyNTA0MjRfMjU5/MDAxNzQ1NDU3NzI3NzI2.raW_SH1uYe6vgH0SVrdMGJ92iucnYAh91CREG0bpDjYg.fV4Xgn4wYvba7AWNQdmE7QzWgTeQVHSEvFJYs6tomP4g.JPEG/20250409_135039.jpg.jpg",
          "https://ldb-phinf.pstatic.net/20250422_241/17452949149373Cr4z_PNG/jevi_%C0%CC%B9%CC%C1%F6%BE%F7%B7%CE%B5%E5%BF%EB-23.png",
          "https://pup-review-phinf.pstatic.net/MjAyNTA2MjZfMTg5/MDAxNzUwOTM1NTI3Nzc2.xGw941uuVT9t_3RyfTxH-XtWMQECU9EWcFx5ABPCJg0g.P1s0amJaoG1fViT6OlUd5FRAdlDGwuhPdhRo_VEf6dwg.JPEG/1000136257.jpg.jpg",
          "https://ldb-phinf.pstatic.net/20250422_31/1745294150223Y8QmK_PNG/jevi_%C0%CC%B9%CC%C1%F6%BE%F7%B7%CE%B5%E5%BF%EB-25.png",
          "https://pup-review-phinf.pstatic.net/MjAyNTA1MjFfNjcg/MDAxNzQ3Nzk3MDAwMzIy.GsG-mdORsdoYtxrlYboNnO3zta2Ka4eV1IsFKkLHA6Eg.mS0-b3KtA59klxoLyoQQbAFWCFUrwIdq2p9N8IGfJ5Eg.JPEG/3DFA2BF9-0032-4D19-9639-5378AA5D490D.jpeg",
          "https://ldb-phinf.pstatic.net/20250422_190/1745294154989vSLUC_PNG/jevi_%C0%CC%B9%CC%C1%F6%BE%F7%B7%CE%B5%E5%BF%EB-26.png",
          "https://pup-review-phinf.pstatic.net/MjAyNTA1MDNfMzkg/MDAxNzQ2MjUyNTUwNTc2.CaLSzYw8KW0a3bGf0TBWWs2gCK0i_sT7CphuilRqM0Yg.1iib2aCTrVyZ13kJjSsFELizBnmMLtyB8JTss_BD8Hwg.JPEG/20250503_134916.jpg",
          "https://pup-review-phinf.pstatic.net/MjAyNTA0MjhfMTI3/MDAxNzQ1ODM0Mjg3NjEy.wLNHLaG_JZWcGtsV11sS7pFaR4ay8lLyLUHz6bpmRhYg.n1JDP6W8qrROJy8Z-vP8D61b_ewlsgoliTuSmX45nYQg.JPEG/1E598310-0E5C-4C57-B264-32D1F3775422.jpeg",
          "https://pup-review-phinf.pstatic.net/MjAyNTA3MDlfMjY5/MDAxNzUyMDU2NDI5MDQ4.rlI7NT_lqSWaQO5lippz0j67_8XRDw4OfX3na6VN52og.E36AuvmOVR1F8Lw6TDz_EiGSdcrSwF0-GjxJZiNdbYYg.JPEG/D61F3829-EBC8-439F-BD3F-13DEF76B1B6E.jpeg"
        ],
        "marker": "nres://marker/00079-00145",
        "markerSelected": "nres://marker/00079-00309",
        "markerId": "220053",
        "bizhourInfo": null,
        "hasBroadcastInfo": false,
        "broadcastInfo": null,
        "michelinGuide": null,
        "reservation": null,
        "hasSmartOrder": false,
        "hasNPay": false,
        "reservationLabel": {
          "preOrder": false,
          "standard": false,
          "table": false,
          "takeout": false
        },
        "contentsInfo": null,
        "ratingInfo": null,
        "reviewDisplay": []
      },
      {
        "rank": 12,
        "id": "1780027811",
        "name": "횟집역",
        "x": "126.9674295",
        "y": "37.5577113",
        "distance": 0.033,
        "categoryName": "생선회",
        "categoryPath": [
          [
            "220036",
            "220037",
            "220076",
            "220792",
            "221629"
          ]
        ],
        "category": [
          "한식",
          "생선회"
        ],
        "reviewCount": 271,
        "averagePrice": 20000,
        "address": "서울특별시 중구 중림동 325-1 횟집역",
        "roadAddress": "서울특별시 중구 중림로 40",
        "abbrAddress": "중림동 325-1 횟집역",
        "shortAddress": [
          "서울 중구",
          "중림로 40"
        ],
        "displayContext": [],
        "labelTheme": "점심특선",
        "microReviews": [
          "가성비 최고의 신선한 회와 요리들"
        ],
        "cardDescription": "가성비 최고의 신선한 회와 요리들",
        "description": "특별한 분위기의 맛있고 싱싱한 횟집을 찾으시나요?  '여기가 횟집이야?' '분위기가 이런 횟집이 있어?' '횟집에서 피자를 판다고??'  회식 손님, 커플 손님 등 다양한 손님분들이 자주 하시는 말 ",
        "images": [
          "https://pup-review-phinf.pstatic.net/MjAyNTA1MDhfMTYg/MDAxNzQ2NjcxNzI2NTEy.uSluRCdTOCM3xVX5vPbRrxHNJeOn93--Z928Ad_JJ1gg.8uK_9OZu8Ds3aHM9QaKU9YZuo_81QqbLIC7vou_pbh4g.JPEG/370DF49E-5ABD-4770-9AF6-546F7420E801.jpeg",
          "https://pup-review-phinf.pstatic.net/MjAyNTA1MDVfMjI2/MDAxNzQ2NDM5OTg3Mjkz.3vVccvfKEeCngnNzET68_yzO4YrpE5CxeexCfqw-5WYg.t-R293osNuWOnbjXeg0jA-Gq2ZD0M6vm8UR8K8FKuz0g.JPEG/AEE01A84-AC62-49A4-9A7C-6B5075F8CED6.jpeg",
          "https://ldb-phinf.pstatic.net/20230510_228/1683725080140V5C5U_JPEG/IMG_8715.jpeg",
          "https://pup-review-phinf.pstatic.net/MjAyNTA3MjlfOTMg/MDAxNzUzNzYwMzgwOTU3.Qmu2j_XjmeyJiHRQmrfVFP607ICM3nHnn44Q2f-6oQYg.T18lPgl0nxd567hJ3Tb_ad0jA0vUM8WmGZV55IJ5abog.JPEG/20250729_121834.jpg.jpg",
          "https://naverbooking-phinf.pstatic.net/20221018_172/1666081850833nPMy5_JPEG/KakaoTalk_20221018_171938493_07.jpg",
          "https://pup-review-phinf.pstatic.net/MjAyNTA4MDdfNTIg/MDAxNzU0NTQ0NjUyMTk2.QFYD5eRqgOOir2bSyqQCcJvaRo9M4oqQFXSZopKEJ-Eg.G9xGWmx2ASodk8kAa5wXODXYAkYV1tY9VdAXKKcA6HUg.JPEG/IMG_9427.jpg",
          "https://ldb-phinf.pstatic.net/20230510_285/1683725079520MLvsa_JPEG/IMG_8736.jpeg",
          "https://pup-review-phinf.pstatic.net/MjAyNTA2MTlfNTcg/MDAxNzUwMzA5MTU3ODQy.72xl1nbV9SYmD_LhKmPxk2-z07zWYkbEFo7ntsyRM2og.k6eNcVTvDFRf7-ZHMlQB_5UYI5FaHHTZOcRvSoAMdLEg.JPEG/1750308990132.jpg.jpg",
          "https://pup-review-phinf.pstatic.net/MjAyNTA2MzBfMjA2/MDAxNzUxMjg5MDEwODQ0.xa4d7noir9LmIIu_VuvVbL3HT5ZVqa7tX8GcKZiCVhMg.PfLp2DS4eS96LQG3VMQU6n6DEVxiMlU-EpA0VfNtN5kg.JPEG/20250630_205300.jpg.jpg",
          "https://pup-review-phinf.pstatic.net/MjAyNTEwMTRfNDIg/MDAxNzYwNDEyNzk3NjIx.Yd5ZjKzZgH6HNgK8PIYzsOIFh8K4hw__l2dxcFeCp-kg.voAUcT4sBOcSqrt2dFCcIVfby817AgeVaQVnqWbLRyYg.JPEG/20251014_121246.jpg.jpg"
        ],
        "marker": "nres://marker/00079-00145",
        "markerSelected": "nres://marker/00079-00309",
        "markerId": "221629",
        "bizhourInfo": null,
        "hasBroadcastInfo": false,
        "broadcastInfo": null,
        "michelinGuide": null,
        "reservation": null,
        "hasSmartOrder": false,
        "hasNPay": false,
        "reservationLabel": {
          "preOrder": false,
          "standard": true,
          "table": false,
          "takeout": false
        },
        "contentsInfo": null,
        "ratingInfo": {
          "total": "4.83",
          "receipt": null,
          "booking": null
        },
        "reviewDisplay": [
          {
            "sid": "1780027811",
            "bodySummary": "서울역 중림동 감성 횟집 서울 중구 중림로 40 횟집역 0507-1319-9293 서울역 근처 신상 감성 횟집 주차보다는 도보 추천 화장실 내부에 있음 깨끗! 뭔가 신상느낌이 나는",
            "url": "https://m.blog.naver.com/sunsuwoni/223375970073",
            "nick": "우주가든",
            "profileImg": "http://blogpfthumb.phinf.naver.net/MjAyMzA5MDJfMjM0/MDAxNjkzNjI1MjYxMDE1.S8rmNn-QLlLBjgDcdts4xMK5phOOwTeK7X341H0lUrAg.x6Jvo6jGJ9nvedqzlxP7LU0TUR7qo2cqng9JmMRHS0Ag.PNG.sunsuwoni/profileImage.png"
          },
          {
            "sid": "1780027811",
            "bodySummary": "가격대가 있는 횟집였는데 기본 스끼다시는 부실했으나 내가 좋아하는 완두콩,번데기, 감튀 옥수수콘치즈 몬가 요상한 조합이지만 감튀와 콘치즈가 젤 맛났다 테이블 키오스크 보니 신청곡을",
            "url": "https://m.blog.naver.com/sunnie_1003/223343691283",
            "nick": "소니",
            "profileImg": "http://blogpfthumb.phinf.naver.net/MjAyMzEyMjFfMTI4/MDAxNzAzMTQ4ODU5MDAz.2mJUI8s4An7u5vXzl3Ura3cV6Nfgpg5Ue248LTevCgQg.T1VE6p1ljZ6SrGvp_UHaQgTlHCjtUAHpLWN5cPN1SpUg.JPEG.cuimeixian/profileImage.jpg"
          },
          {
            "sid": "1780027811",
            "bodySummary": "[서울/중구] 서울역 충정로 피자를 파는 감성횟집 회맛집 힙한 회식장소 '횟집역' 퓨전회펍집 방문 맹거니의 내돈내산 밥상 네이버예약으로 방문하여 남기는 내돈내산 리뷰 인증! 위치는",
            "url": "https://m.blog.naver.com/mgeona/223335716515",
            "nick": "맹거니",
            "profileImg": "http://blogpfthumb.phinf.naver.net/MjAyNDAxMDhfMjUz/MDAxNzA0Njk0NDI5MTE0.D9vCILJG9MtkDWj1An2iReenf1LnVXdp4Nd0_IvPjaUg.ga8SGs6_KrdY62M9hBz_zC6o4jaQIZFrKZv2lx_MgEIg.JPEG.codehopper/%25EB%25A7%25B9%25EA%25B1%25B0%25EB%258B%2588_%25EB%25A1%259C%25EA%25B3%25A0_%25ED%259D%25B0%25EC%2583%2589.jpg/%25EB%25A7%25B9%25EA%25B1%25B0%25EB%258B%2588_%25EB%25A1%259C%25EA%25B3%25A0_%25ED%259D%25B0%25EC%2583%2589.jpg"
          },
          {
            "sid": "1780027811",
            "bodySummary": "여기는 단체 모임 2차하기 딱인데 왜냐하면 횟집인데 호프집이기 때문이다 ㅎ(무슨말) 위치는 서울역 뒷편 충정로 근방이다 ✔영업시간 : 월-토 17:00-23:30 매장 입구! 매장",
            "url": "https://m.blog.naver.com/9412js/223155583862",
            "nick": "쑤기",
            "profileImg": "http://blogpfthumb.phinf.naver.net/MjAyMzAxMjNfMjcz/MDAxNjc0NDY3NjIyODU5.toO7jJNTmJrB1BJVktIhHdGfi_8JRdEiCP4vCm7_MRAg.gWHbQs4Xg-xPoIGn8SG3J4zJ4sVo-vBxhVw8EraWAdMg.PNG.9412js/profileImage.png"
          },
          {
            "sid": "1780027811",
            "bodySummary": "5 5점 만점에 점 팀장님께서 돈까스 먹으러 데려가 주셨던, 예전에 회먹으러 오게 된 '풀그라운드' '횟집역' 욕심쟁이인 곳이라 상호가 2개나 된다. 가게 외관 외부 간판 외부 간",
            "url": "https://m.blog.naver.com/ohri2252/223136469714",
            "nick": "오해",
            "profileImg": "http://blogpfthumb.phinf.naver.net/MjAyMjEyMjFfMTUz/MDAxNjcxNjA0Njg0MTAx.pMrTs0qoIisCH_lze7CspoNleLoJYr326Qfng5KoCMsg.tDZ62fsI8ThW84-f2xwplCRcZfO0AHOr9IZ2XoEtcKEg.PNG.ohri2252/profileImage.png"
          }
        ]
      },
      {
        "rank": 13,
        "id": "795112914",
        "name": "우진갈비",
        "x": "126.9666956",
        "y": "37.5581425",
        "distance": 0.05,
        "categoryName": "육류,고기요리",
        "categoryPath": [
          [
            "220036",
            "220037",
            "220075",
            "220733"
          ]
        ],
        "category": [
          "한식",
          "육류,고기요리"
        ],
        "reviewCount": 1577,
        "averagePrice": 30000,
        "address": "서울특별시 중구 중림동 200 삼성 사이버 빌리지 아파트상가 3동 101호 우진갈비",
        "roadAddress": "서울특별시 중구 중림로 10",
        "abbrAddress": "중림동 200 삼성 사이버 빌리지 아파트상가 3동 101호 우진갈비",
        "shortAddress": [
          "서울 중구",
          "중림로 10"
        ],
        "displayContext": [
          "돼지갈비",
          "냉면",
          "고기집",
          "점심특선",
          "고급진"
        ],
        "labelTheme": "분위기 좋은",
        "microReviews": [],
        "cardDescription": "우진갈비는 좋은 재료와 정성으로 만든 장인의 갈비 입니다. 엄선한 원육과 장인정신으로 재워낸 양념갈비의 맛을 느껴보세요, 20년이상 경력의 조리장이 정성으로 직접 끓이는 명품 갈비탕,  ",
        "description": "우진갈비는 좋은 재료와 정성으로 만든 장인의 갈비 입니다. 엄선한 원육과 장인정신으로 재워낸 양념갈비의 맛을 느껴보세요, 20년이상 경력의 조리장이 정성으로 직접 끓이는 명품 갈비탕,  ",
        "images": [
          "https://pup-review-phinf.pstatic.net/MjAyNTEwMjVfMTc0/MDAxNzYxMzg5OTgxMjkx.rb99Q1-cOR-baSxn4u8t3pCx8V2wErCuDlOer6KK-Sgg.SFKTZNWAODef_VfJB4sNmkC4JP8_NOfjf8oMXabCT5Eg.JPEG/B833A537-7324-4C20-B12C-8229EE5051A8.jpeg",
          "https://pup-review-phinf.pstatic.net/MjAyNTA3MjJfMTQy/MDAxNzUzMTgxMzMyNjAw.iTq5aLWiKqt-KwCzzuqiFh7Ff5vN3bXmfZV9dNQ9uTUg.GsmhFSwgd-87v77asfs9_IxHhCEHcndHZSlTvNLsYh0g.JPEG/20250719_173018.jpg.jpg",
          "https://ldb-phinf.pstatic.net/20250223_161/1740278173418zTamD_JPEG/%C6%E4%C0%CC%C1%F61.JPG",
          "https://pup-review-phinf.pstatic.net/MjAyNTA2MTZfMjc2/MDAxNzUwMDY4NDI0ODQ5.hwYxJjW_W75lKXIRM-Blone5ntLdQoSD5bDwbGC4DQYg.YtvB7OwFjJS6Bv9CZcbVYhXJzsLiX4zeOvjCUOoqz9gg.JPEG/20250616_140311.jpg.jpg",
          "https://ldb-phinf.pstatic.net/20250223_71/1740278173406Dhm6N_JPEG/%C6%E4%C0%CC%C1%F62.JPG",
          "https://pup-review-phinf.pstatic.net/MjAyNTA3MzBfNzEg/MDAxNzUzODgwOTAxNjM4.Yj33olBZmPdtZ-E17ll8UvyH16LET0sME6m_9JIM24Ag.xJ6vYm7IoSag2eI3_oE8-0p638M2x5vzh1fm46EEOhwg.JPEG/20250729_113403.jpg",
          "https://ldb-phinf.pstatic.net/20250223_84/1740278173432iVSG6_JPEG/%C6%E4%C0%CC%C1%F63.JPG",
          "https://pup-review-phinf.pstatic.net/MjAyNTA4MThfMTM2/MDAxNzU1NDgyMTkyMjU3.jakQ8wLtzs6jk96WKx5iWr1YiAjNxm_A0TIoq_rkekog.jYbShusYjHqAqoi5EVaS_dEwwzKtrRb_l6waMtB9LQUg.JPEG/20250802_213026.jpg.jpg",
          "https://pup-review-phinf.pstatic.net/MjAyNTEwMjRfMTQx/MDAxNzYxMjg3OTU1MTQ2.e83HdWbH6mFz1WsowDtIQ2XEXMkXgHytrJ05p7rNHnIg.PIppp1o4PUFa-tcmE4KA9pDGrj6zdOHnZ7SMkj-zYYQg.JPEG/20251016_114026.jpg",
          "https://pup-review-phinf.pstatic.net/MjAyNTA0MjNfMzgg/MDAxNzQ1MzU1NDUyNzg5.xzUpGlsM9xwgBEV2wyiB7t4UeodIC3csDqz-cVWQRScg.QWZxRbRNYWt5ZSSZJjqLNkf7VBlo5_dkJALeDPyvISAg.JPEG/20250420_195935.jpg.jpg"
        ],
        "marker": "nres://marker/00079-00145",
        "markerSelected": "nres://marker/00079-00309",
        "markerId": "220733",
        "bizhourInfo": null,
        "hasBroadcastInfo": false,
        "broadcastInfo": null,
        "michelinGuide": null,
        "reservation": null,
        "hasSmartOrder": false,
        "hasNPay": false,
        "reservationLabel": {
          "preOrder": false,
          "standard": true,
          "table": false,
          "takeout": false
        },
        "contentsInfo": null,
        "ratingInfo": null,
        "reviewDisplay": [
          {
            "sid": "795112914",
            "bodySummary": "갈비탕,돼지갈비,육회 점심메뉴도 다양하고 회식장소로도 좋은식당 운영시간 화 11:00- 22:30 15:00 - 16:30 브레이크타임 22:00 라스트오더 서울역 근처이면서 충정",
            "url": "https://m.blog.naver.com/enqn326/223369028026",
            "nick": "믄지",
            "profileImg": "http://blogpfthumb.phinf.naver.net/MjAyNDAxMTRfMjQx/MDAxNzA1MjEyNzkzMzkw.-VF90c1a18hgnMV8Ei8XqRhwYVZnxgnHc7Jo0k684skg.bqT0OwC4kQcNWrSYkQyKpVgrghrH1wcDO7X-9Ot5ogcg.JPEG.enqn326/%25EB%258B%25A4%25EC%259A%25B4%25EB%25A1%259C%25EB%2593%259C.jpg/%25EB%258B%25A4%25EC%259A%25B4%25EB%25A1%259C%25EB%2593%259C.jpg"
          },
          {
            "sid": "795112914",
            "bodySummary": "식당은 이렇게 칸막이 쳐져있는 곳도 있어서 뻥 뚫려 있는 느낌이 아니어서 좋았어요!!!완전히 막혀있는 느낌은 아니었지만 칸막이가 쳐져있으면 왠지모르게 편안한게 다들 아시져?? ㅎㅎ",
            "url": "https://m.blog.naver.com/wlstn291/223343487980",
            "nick": "수수v",
            "profileImg": "http://blogpfthumb.phinf.naver.net/MjAyMzEwMDlfMjQg/MDAxNjk2NzkxMjA1MzIy.yQ51Ck7mrIAPFeFTuBCrlQChUbB_1H_zxgCOG0-ABx0g.dOOYj57SsbWrWVfsoQ_POiyAF23n-5BRkpgX4T1Fi_gg.JPEG.wlstn291/33333333333.jpg/33333333333.jpg"
          },
          {
            "sid": "795112914",
            "bodySummary": "우진갈비 주소: 서울 중구 중림로 10 삼성 사이버빌리지 아파트상가 3동 101호 영업시간: 매일 11:00~22:30 브레이크타임 15:00~16:30 라스트오더 22시 만리재길",
            "url": "https://m.blog.naver.com/yoom9707/223343175373",
            "nick": "윰",
            "profileImg": ""
          },
          {
            "sid": "795112914",
            "bodySummary": "'우진갈비' 주소 : 서울특별시 중구 중림로 10 영업시간 : 11:00~22:30 브레이크 : 15:00~16:30 연락처 : 0507-1419-6166 예약, 주차, 단체 이용",
            "url": "https://m.blog.naver.com/bofb49/223324479102",
            "nick": "파파카",
            "profileImg": "http://blogpfthumb.phinf.naver.net/MjAyMjA2MDVfMTQz/MDAxNjU0NDEyODIzNjE2.PyebyzTDqvv5BIpeCfGmtPpJZ1Z9FdDbZVdOldr6Nfkg.jY6YnWaTrPfW-Y2O7qIWm8VjTQrtk4jkkcN_INUM4pIg.PNG.bofb49/%25ED%258C%258C%25ED%258C%258C%25EC%25B9%25B43.png/%25E1%2584%2591%25E1%2585%25A1%25E1%2584%2591%25E1%2585%25A1%25E1%2584%258F%25E1%2585%25A13.png"
          },
          {
            "sid": "795112914",
            "bodySummary": "충정로 우진갈비의 점심특선 돼지갈비정식이 그렇게 맛있다는 이야기를 듣고 달려가본 충정로 돼지갈비 맛집 우진갈비! 메뉴판 이미지는 아래로 대신한다 ㅋㅋㅋㅋ 점심특선 메뉴로 나는 돼지",
            "url": "https://m.blog.naver.com/serena220/223315672820",
            "nick": "serena",
            "profileImg": "http://blogpfthumb.phinf.naver.net/MjAyNDAxMjFfMzEg/MDAxNzA1ODQ5MTUxMzg2.NiqOSBbaEBj_hWGcoGY_BBdYQl9g1mVv6k1N-7TRuV0g.4nE-kEGRKLDFDdbMw28N1gleaLHbFCfs_pFWMc8iOn8g.PNG.serena220/profileImage.png"
          }
        ]
      },
      {
        "rank": 14,
        "id": "1730059584",
        "name": "계모임",
        "x": "126.967632",
        "y": "37.5578795",
        "distance": 0.039,
        "categoryName": "치킨,닭강정",
        "categoryPath": [
          [
            "220036",
            "220049",
            "220245"
          ]
        ],
        "category": [
          "음식점",
          "치킨,닭강정"
        ],
        "reviewCount": 269,
        "averagePrice": 20000,
        "address": "서울특별시 중구 중림동 142 1층 2호",
        "roadAddress": "서울특별시 중구 중림로 39",
        "abbrAddress": "중림동 142 1층 2호",
        "shortAddress": [
          "서울 중구",
          "중림로 39"
        ],
        "displayContext": [],
        "labelTheme": "",
        "microReviews": [],
        "cardDescription": "안녕하세요 계모임 충정로 중림동입니다. 항상 저희 계모임을 이용해 주시는 고객님들께 깊은 감사드립니다. 고객 여러분 통닭으로 다이어트가 가능합니다!!! 1시간 반 가량 전기오븐에 돌려서",
        "description": "안녕하세요 계모임 충정로 중림동입니다. 항상 저희 계모임을 이용해 주시는 고객님들께 깊은 감사드립니다. 고객 여러분 통닭으로 다이어트가 가능합니다!!! 1시간 반 가량 전기오븐에 돌려서",
        "images": [
          "https://pup-review-phinf.pstatic.net/MjAyNTA4MTFfMTI0/MDAxNzU0ODYxNDc3MDMw.jSYol6YKR7jyS1SPS-qeSRSq2iM-CKyYCK8geopSMnkg.9DKFqpp4nYzd_84WVYlDkmk8BLezNR4xFOZ9COf_zZUg.JPEG/33DA9A3C-C422-41B2-8E30-0B3FEB01C253.jpeg",
          "https://pup-review-phinf.pstatic.net/MjAyNTEwMjVfMTc3/MDAxNzYxMzg2MDYxMzIw.6wfwfKXbvxLEK0oPXyhmRDF-3-MdELYm422SeVTSIiMg.3qLK9C09VFLWj41UGZQCCM0hghlHZ2K17N0pEFVBD6kg.JPEG/1759569707761.jpg.jpg",
          "https://ldb-phinf.pstatic.net/20250515_92/1747295696510zDRiM_JPEG/IMG_7408.jpeg",
          "https://pup-review-phinf.pstatic.net/MjAyNTA2MjhfMjU1/MDAxNzUxMTExODU2MzQ5.mXUd8z6V7k9PbTbjjdgpUup8r9URbwkoFHZE3mEtNYAg.GdiPczf_xRWmj_19fQUnjWIAwtYriq66DQaDdH0Sc2og.JPEG/2E0FC6DB-4BE7-4E27-9C24-179FA50C4021.jpeg",
          "https://ldb-phinf.pstatic.net/20250515_178/1747295683033wfNQH_JPEG/IMG_7413.jpeg",
          "https://pup-review-phinf.pstatic.net/MjAyNTA1MTFfNTkg/MDAxNzQ2OTM5MTM4OTEz.JbddN65O8-OKXYClX_QLaMGJtTAYS35ymE_pMpfb1iYg.Fjdx-k_o2D9WT6_Pi93cvGp1vQY_pFoqR69AfOOpFl0g.JPEG/BBD4407B-B88B-4D47-9505-FB0A4E434CF7.jpeg",
          "https://ldb-phinf.pstatic.net/20181219_265/15451969274830nuPA_JPEG/jGvfaoIv7yjsGFsEBjP2Vfwx.jpg",
          "https://pup-review-phinf.pstatic.net/MjAyNTA2MjBfMjUw/MDAxNzUwNDA0MzEyOTc3.eP-bgmawZ0S-izQzHibPVyp7cyTP3wtU6OOZysZb8Qgg.Cc0MWAw2oIr0iyHN-FGBjyn5o_aKToy_JttNjq3Jkvgg.JPEG/20250614_182130.jpg.jpg",
          "https://pup-review-phinf.pstatic.net/MjAyNTA5MTNfMjQ2/MDAxNzU3NzY5NjcyODIw.kujt3BY1W29gNpidWPl7ElMj_b-c2oi85WP3tHT85sEg.YL8BTVKRhsbx4_jJtLjIgPiB3XEiq0YIBhcKkSFNIMAg.JPEG/D5AAAC11-AFCB-494E-B82B-78945A53DD8D.jpeg",
          "https://pup-review-phinf.pstatic.net/MjAyNTA5MTJfMjMg/MDAxNzU3NjA1NjE4MzI0.rwAxuokGO8in1weanoUo7-lV1SK047bEMOy4wp0YFgsg.8VDciA7_WF6bBXfUsOV_ZFNKpvgfMWVHjoTet4ed-0Qg.JPEG/CA86B07F-4239-46AF-8DCD-B610195586B5.jpeg"
        ],
        "marker": "nres://marker/00079-00145",
        "markerSelected": "nres://marker/00079-00309",
        "markerId": "220245",
        "bizhourInfo": null,
        "hasBroadcastInfo": false,
        "broadcastInfo": null,
        "michelinGuide": null,
        "reservation": null,
        "hasSmartOrder": false,
        "hasNPay": false,
        "reservationLabel": {
          "preOrder": false,
          "standard": true,
          "table": false,
          "takeout": false
        },
        "contentsInfo": null,
        "ratingInfo": null,
        "reviewDisplay": [
          {
            "sid": "1730059584",
            "bodySummary": "작년에 다녀온 전기구이한방통닭집 이름이 굉장히 긴데여 가게이름은 짧고 특이하답니다 사촌언니가 다녀왔길래 맛있어보여서 저도 가봤는데 존맛탱이라 리뷰 하려고 가져왔습니당 계모임 영업시",
            "url": "https://m.blog.naver.com/zzing_iary/223366542565",
            "nick": "이진갱이",
            "profileImg": "http://blogpfthumb.phinf.naver.net/MjAyMzA0MTlfMTU0/MDAxNjgxODg0NTIwNDcy.nZo1hSyUD85VzbZepAiAswtVpwZVogc34alcM6IBIhUg.HcQw11qHtyoEz6JubwhreqgMowB6K-0bia-QFgQvwF4g.PNG.wlsrud_22/profileImage.png"
          },
          {
            "sid": "1730059584",
            "bodySummary": "바람을 뚫고 먹으러갔어요 ㅎ충정로 계모임 서울 중구 중림로 39 1층 2호 충정로 술집과 밥집이 모여 있는 골목 초입에 위치한 충정로 계모임. . 점심 먹으러 지나다닐 때 눈여겨 ",
            "url": "https://m.blog.naver.com/kakasi95/223288882129",
            "nick": "킴니키",
            "profileImg": "http://blogpfthumb.phinf.naver.net/MjAyMTExMTlfMTE3/MDAxNjM3MzI5NTYyNzc0.lpxVLViQQN_dHrTFvQNgtJZjuR3X_0G32eHlbHlk50wg.LhvJyZwe46YRj_D7ydRSZU5I7jQ2xtjgJ2pp6VHTOBQg.JPEG.kakasi95/KakaoTalk_20211004_103746718.jpg"
          },
          {
            "sid": "1730059584",
            "bodySummary": "계는 하지 않지만 계모임은 가봅시다 노랑 노랑 귀여운 외관 우리는 베스트 메뉴인 콘치즈 한방 통닭 주문 주류는 이 정도 닭은 주문한지 15분 정도 만에 후딱 나온 편 오!!! 비주",
            "url": "https://m.blog.naver.com/butterfly0o0/223244845121",
            "nick": "시작",
            "profileImg": "http://blogpfthumb.phinf.naver.net/data19/2006/10/4/145/%C0%CC%BF%AC%C8%F1-4183-butterfly0o0.gif"
          },
          {
            "sid": "1730059584",
            "bodySummary": "여기가 어디냐면요 충정로 먹자골목이 있습니다. 삼성아파트 라인 그 라인에 있는데 서울로쪽하고 가까운 쪽입니다. 계모임이라고 위치 검색해보니 여기뿐만 아니라 다른곳들도 많이 잡히는거",
            "url": "https://m.blog.naver.com/pjkcon/223051905918",
            "nick": "규니씨이",
            "profileImg": "http://blogpfthumb.phinf.naver.net/MjAyNDAyMTlfMTEx/MDAxNzA4Mjk1MjAxODUx.zKlpnD2V3dg_7mAQUHt-t2hQl2l3OV91lLQQ7gxAQYEg.KPbNWHTaY6BK5DrZ6SJ_KhbWrZbA9gohRsBREoRB99Mg.PNG.pjkcon/20240219_072453.png/20240219_072453.png"
          },
          {
            "sid": "1730059584",
            "bodySummary": "메뉴판 BEST 메뉴인 #콘치즈한방통닭 27000원 으로 주문 미리 주문을 해서 생각보다 금방나옴! 둘이 먹기에 충분하지만 탄수화물이 부족하기에 #차돌된장라면 도 주문.. 스프 +",
            "url": "https://m.blog.naver.com/eskim112/223049498403",
            "nick": "유리아쥬",
            "profileImg": "http://blogpfthumb.phinf.naver.net/20160210_173/eskim112_14550755796740OgXT_JPEG/KakaoTalk_20160210_123849429.jpg"
          }
        ]
      },
      {
        "rank": 15,
        "id": "1037256281",
        "name": "김영희아구찜&코다리냉면 충정로점",
        "x": "126.9670225",
        "y": "37.5582677",
        "distance": 0.04,
        "categoryName": "아귀찜,해물찜",
        "categoryPath": [
          [
            "220036",
            "220037",
            "220076",
            "220793",
            "221633"
          ]
        ],
        "category": [
          "한식",
          "아귀찜,해물찜"
        ],
        "reviewCount": 559,
        "averagePrice": 10000,
        "address": "서울특별시 중구 중림동 150-1 이화빌딩1층",
        "roadAddress": "서울특별시 중구 중림로 31",
        "abbrAddress": "중림동 150-1 이화빌딩1층",
        "shortAddress": [
          "서울 중구",
          "중림로 31"
        ],
        "displayContext": [],
        "labelTheme": "부모님과 함께",
        "microReviews": [
          "신선한 재료로 완성된 해물찜의 풍미"
        ],
        "cardDescription": "신선한 재료로 완성된 해물찜의 풍미",
        "description": "해물요리 전문점 김영희아구찜입니다. 점심시간은 찜정식(코다리,아구)이 대표 메뉴로 직장인들에게 인기가 많고 특히 가격할인도 합니다. 저녁 메뉴로는 아구찜과 해물찜,코다리찜에 통문어 ",
        "images": [
          "https://pup-review-phinf.pstatic.net/MjAyNTA1MzFfMjI1/MDAxNzQ4NjkzNDg2ODg1.LNpB_0YS8r1TyIoRzxqpzE5ADBqtao--HuCO18uRoZQg.KByBgGbfwqUHQDxvP30_wUAQwtdRLGmB5HBVt0HzZ6wg.JPEG/E05E5EE6-CC3B-4B1A-8288-2D432C1B1F6D.jpeg",
          "https://pup-review-phinf.pstatic.net/MjAyNTA0MjZfNzMg/MDAxNzQ1NjcwNjk3NjEy.VgL_LKxtwRqq2JpgcQqT4NMQN7Rl4bf2juW5qumCaygg.eobcJcoyQtiCcKOOhyGbHdInaVOnrUoAyoaIj4JBleIg.JPEG/20250426_192639_HDR.jpg.jpg",
          "https://ldb-phinf.pstatic.net/20240930_96/1727659140526iNrLp_JPEG/image.jpg",
          "https://pup-review-phinf.pstatic.net/MjAyNTA1MzBfNjEg/MDAxNzQ4NjAwMzYzNjA4.TwGOsHC7r8XSICKQDKSyvbEHrw663pavSChbdAipiLwg.PBcwp_WHAH_hyEEZ7IqdFCam9dkbbzdwcO_req7B9PQg.JPEG/942506F0-B04A-4A72-9685-30AE97AFF7CF.jpeg",
          "https://ldb-phinf.pstatic.net/20240930_223/1727659177448i5LCB_JPEG/image.jpg",
          "https://pup-review-phinf.pstatic.net/MjAyNTA0MDdfMTc5/MDAxNzQ0MDIzMDYzNzg2.nLx4XjxAyHaFcOC1qBxYmeRiEdgErH_409SKvtYikagg.vF7vn_hUMbjeTmqLD9HhXrNEXXXvhWeGPLWn4sNotbcg.JPEG/20250407_190037.jpg.jpg",
          "https://ldb-phinf.pstatic.net/20240921_282/1726888833293X2aXu_JPEG/IMG_2251.jpeg",
          "https://pup-review-phinf.pstatic.net/MjAyNTA0MTZfMTEx/MDAxNzQ0NzY4NTgxOTA0.vRhgiZVL1RUhltF_op9D7wSJNDNoNeiA3vDJPimgI0cg.7ZMivARP9Ge1A8UC01hBbATlpzBJ1AAbrnYay1GB5VEg.JPEG/396F11F0-5A78-498D-9AC5-ABA1D37C2B0A.jpeg",
          "https://pup-review-phinf.pstatic.net/MjAyNTA3MDJfODQg/MDAxNzUxNDMwMjE2NzY2.BwgunTlniGxDP2zi3dFfNAxPlQJ6ndj2TOcUZ5l3pFMg.3-N1RpW3HKjofytHZ4nOZE1x59gVSm2r-T0Nc8Seyo8g.JPEG/20250702_131749.heic.jpg"
        ],
        "marker": "nres://marker/00079-00145",
        "markerSelected": "nres://marker/00079-00309",
        "markerId": "221633",
        "bizhourInfo": null,
        "hasBroadcastInfo": false,
        "broadcastInfo": null,
        "michelinGuide": null,
        "reservation": null,
        "hasSmartOrder": false,
        "hasNPay": false,
        "reservationLabel": {
          "preOrder": false,
          "standard": false,
          "table": false,
          "takeout": false
        },
        "contentsInfo": null,
        "ratingInfo": null,
        "reviewDisplay": [
          {
            "sid": "1037256281",
            "bodySummary": "가격은 1만2천9백원 1인당 이정도 가격인데 뭐 이정도면 나름 합리적 아주 싼 건 아니지만 비싸지도 않은 수준 다른 식사류도 있긴한데 며 2~3천원 상간이라면 다른 메뉴보단 저 정",
            "url": "https://m.blog.naver.com/pjkcon/223341300900",
            "nick": "규니씨이",
            "profileImg": "http://blogpfthumb.phinf.naver.net/MjAyNDAyMTlfMTEx/MDAxNzA4Mjk1MjAxODUx.zKlpnD2V3dg_7mAQUHt-t2hQl2l3OV91lLQQ7gxAQYEg.KPbNWHTaY6BK5DrZ6SJ_KhbWrZbA9gohRsBREoRB99Mg.PNG.pjkcon/20240219_072453.png/20240219_072453.png"
          },
          {
            "sid": "1037256281",
            "bodySummary": "주소: 서울 중구 중림로 31 *KTX서울역에서 630m, 2ㆍ5호선 충정로역 5번 출구에서 309m ㆍ전화: 0507-1497-6679 ㆍ영업: 11:00 - 21:00(매주 일",
            "url": "https://m.blog.naver.com/kbell21/223335358360",
            "nick": "풍동거사",
            "profileImg": "http://blogpfthumb.phinf.naver.net/20230914_279/kbell21_1694642518073HsQHM_JPEG/image.jpg"
          },
          {
            "sid": "1037256281",
            "bodySummary": "메뉴는 '코다리, 아구, 낙지' 등 대표적인 것만 주문할 수 있는데 11시 30분 이후로는 손님들이 많아서 웨이팅을 해야할 수도 있어요. ㅎㅎ 밑반찬으로는 샐러드, 깍뚜기는 항상 ",
            "url": "https://m.blog.naver.com/bofb49/223288381757",
            "nick": "파파카",
            "profileImg": "http://blogpfthumb.phinf.naver.net/MjAyMjA2MDVfMTQz/MDAxNjU0NDEyODIzNjE2.PyebyzTDqvv5BIpeCfGmtPpJZ1Z9FdDbZVdOldr6Nfkg.jY6YnWaTrPfW-Y2O7qIWm8VjTQrtk4jkkcN_INUM4pIg.PNG.bofb49/%25ED%258C%258C%25ED%258C%258C%25EC%25B9%25B43.png/%25E1%2584%2591%25E1%2585%25A1%25E1%2584%2591%25E1%2585%25A1%25E1%2584%258F%25E1%2585%25A13.png"
          },
          {
            "sid": "1037256281",
            "bodySummary": "황태국이랑 비빔밥, 코다리찜이 나오는~~~ 이곳은 김영희 아구찜&코다리냉면!! 낙지볶음 코다리찜 간이 짭쪼름하고, 시래기와 잘 어울려요~~ 탕이랑 찜, 비빔밥, 반찬이 모두 맛있어",
            "url": "https://m.blog.naver.com/gkszjq/223284955795",
            "nick": "한가로이",
            "profileImg": "http://blogpfthumb.phinf.naver.net/MjAyMTA5MDdfMTQw/MDAxNjMwOTc4OTUwMDUx.D1cDVNoBqJFC80RGiY5YcLUrw0yux_LI9HO09FWvZwcg.VdZJrjIFlohw-zC-2btkvZawd9yolxY9wgUbHwivogAg.PNG.gkszjq/profileImage.png"
          },
          {
            "sid": "1037256281",
            "bodySummary": "달달한 소스에 부드러운 코다리살이 가득! 서부역 충정로 맛집 김영희 아구찜 코다리냉면 위치: 서울특별시 중구 중림로31 영업시간: 11:00 - 21:00(브레이크 타임 15:00",
            "url": "https://m.blog.naver.com/sumika1207/223199194503",
            "nick": "언제나맑음",
            "profileImg": "http://blogpfthumb.phinf.naver.net/data43/2009/3/27/234/npecab3_marsss7-sumika1207.jpg"
          }
        ]
      },
      {
        "rank": 16,
        "id": "38281188",
        "name": "석돈",
        "x": "126.9673514",
        "y": "37.5577602",
        "distance": 0.024,
        "categoryName": "육류,고기요리",
        "categoryPath": [
          [
            "220036",
            "220037",
            "220075",
            "220733"
          ]
        ],
        "category": [
          "한식",
          "육류,고기요리"
        ],
        "reviewCount": 410,
        "averagePrice": 30000,
        "address": "서울특별시 중구 중림동 325-1 2층 석돈",
        "roadAddress": "서울특별시 중구 중림로 40",
        "abbrAddress": "중림동 325-1 2층 석돈",
        "shortAddress": [
          "서울 중구",
          "중림로 40"
        ],
        "displayContext": [
          "스테이크",
          "카르보나라",
          "바게트",
          "정육식당",
          "돈가스"
        ],
        "labelTheme": "한식",
        "microReviews": [],
        "cardDescription": "석돈은 서울 중구 중림로40에 위치한 돼지고기 전문점으로 충정로역과 서울역에서 도보로 접근이 용이합니다 석돈은 장수에서 특수 제작된 돌판을 사용하여 돼지고기를 구워내는 것이 특징입 ",
        "description": "석돈은 서울 중구 중림로40에 위치한 돼지고기 전문점으로 충정로역과 서울역에서 도보로 접근이 용이합니다 석돈은 장수에서 특수 제작된 돌판을 사용하여 돼지고기를 구워내는 것이 특징입 ",
        "images": [
          "https://pup-review-phinf.pstatic.net/MjAyNTA5MjVfMjIy/MDAxNzU4Nzk3OTYyMTcx.7hvL5APLYg7HmL74mEZGMUKRprw876TgKK7n4HrTgLEg.TSOHH0b0ZX4Vbf5ksktec5x1nsZtkzOC8fs0GRl6NTYg.JPEG/IMG_1427.jpeg",
          "https://pup-review-phinf.pstatic.net/MjAyNTA0MzBfMjgz/MDAxNzQ2MDExOTQ2Mzkx.5cjyGwRy4Uhv7EEuPvgjs4EClIy8CRQln636YrQ-IbUg.MsrlUBrOlUP-MAH9unXmEnWYz2CEKXpAGLx_UNmdf-4g.JPEG/1000017063.jpg",
          "https://ldb-phinf.pstatic.net/20250326_224/1742977611429mPOrU_JPEG/KakaoTalk_20250325_180322973_01.jpg",
          "https://pup-review-phinf.pstatic.net/MjAyNTA2MjVfMjY5/MDAxNzUwODU1NzMwNDMy.VFzol_0uCB72L0BoWlmIbrZNAgdks_Q247cRn4LJ9Jwg.lIbdgfKc2i80pLoM1P_MUfIkJgEwZAkfNTE1MhpChw0g.JPEG/IMG_6089.jpeg",
          "https://ldb-phinf.pstatic.net/20250326_103/1742977611395PergM_JPEG/KakaoTalk_20250325_180322973_21.jpg",
          "https://pup-review-phinf.pstatic.net/MjAyNTA0MDFfMTY0/MDAxNzQzNTAxNzYxNjU1.WE6aOvQrzfrq1h842V2TGt9BSaVVn6hDMuwjBTIVcVwg.v801LCMpF0S-Oqal_146IN9qmO2bvZjMi6ZBAtYSuUog.JPEG/IMG_5422.jpeg",
          "https://ldb-phinf.pstatic.net/20250326_196/1742977611449kIpzl_JPEG/KakaoTalk_20250325_180322973_22.jpg",
          "https://pup-review-phinf.pstatic.net/MjAyNTA1MTBfMTU5/MDAxNzQ2ODY2MzcyODAx._HSjMvT1pDFph3DD-hklvBH02EhOId3zrxC9RFjH5_4g.p9BpolB_rFVsfemWhjJgymwtF1Kk8bOWu4aTm84T3i8g.JPEG/IMG_7694.jpeg",
          "https://pup-review-phinf.pstatic.net/MjAyNTAzMjlfOCAg/MDAxNzQzMjQyNDY2NTI4.i3BgUwAJGC8dNZ4OhR00odfSBjjQGR-dqiiNXqkQ7Ikg._s-wv5bE_mC_IrIhADp2dothqbXWWrbRdR4ygYy6OFwg.JPEG/20250329_181931.jpg.jpg",
          "https://pup-review-phinf.pstatic.net/MjAyNTA0MjlfMTQw/MDAxNzQ1OTIxNDc2Mjk3.JtNL4RSP3Zggews6mS9rilLYxiyr6HJ7gH1HUloPDdEg.oIWTeVUe9AyCreCl4Xiqbqrcu-Utz0mZ9g9421G658Eg.JPEG/DBC1A0B5-E095-4F9C-8BF0-A726AE99CACB.jpeg"
        ],
        "marker": "nres://marker/00079-00145",
        "markerSelected": "nres://marker/00079-00309",
        "markerId": "220733",
        "bizhourInfo": null,
        "hasBroadcastInfo": false,
        "broadcastInfo": null,
        "michelinGuide": null,
        "reservation": null,
        "hasSmartOrder": false,
        "hasNPay": false,
        "reservationLabel": {
          "preOrder": false,
          "standard": true,
          "table": false,
          "takeout": false
        },
        "contentsInfo": null,
        "ratingInfo": null,
        "reviewDisplay": [
          {
            "sid": "38281188",
            "bodySummary": "오늘은 엄마가 좋아하는 단골 가게 소개하러 왔습니당 매일 11:30~24:00 브레이크 타임 : 평일 15:00~17:00 저 파란 간판이 바로 풀그라운드! 풀그라운드 내부에는 테",
            "url": "https://m.blog.naver.com/haru_memory/222026654724",
            "nick": "하루",
            "profileImg": "http://blogpfthumb.phinf.naver.net/MjAyNDAyMTlfMjYz/MDAxNzA4MzQ1NzY1MjQz.WhCs6bT9PMo-T_BLuRcq0oJpJnvJizI8G27EkU09IY0g.rRZsINTNUilIdKzJnJM6Ii7urQU5N_1cyQV3RgATXQog.PNG/profileImage.png"
          },
          {
            "sid": "38281188",
            "bodySummary": "100g당 1만1,500원이니 꽤나 저렴하죠. 폭풍 흡입하기 바빠서 사진은 영 시원찮습니다. ^^; 식사용 된장국도 기가 막히네요. 점심, 저녁 회식 성지라 해도 될듯. 중리단길 ",
            "url": "https://m.blog.naver.com/postman6666/221463640300",
            "nick": "Poktan News",
            "profileImg": "http://blogpfthumb.phinf.naver.net/20150924_202/postman6666_1443081897320ANdYz_JPEG/%B0%B6%B7%AF%B8%AE%C8%B0%BF%EB.jpg"
          },
          {
            "sid": "38281188",
            "bodySummary": "서울역 7017에서 가까운 스테이크집 풀그라운드! 맘편하게 먹다가 바로 알바가려고 밥 어디서먹을지 고민하다 요기로 왔다 사실 알바하는가게 바로 옆인데도 이곳의 존재를 이날에야 알았",
            "url": "https://m.blog.naver.com/hye0702won/221372378448",
            "nick": "회탈",
            "profileImg": "http://blogpfthumb.phinf.naver.net/MjAyMjEyMzBfOCAg/MDAxNjcyMzc2ODk0MTU3.UZnM4Oi2_P5LJ6AyF-dGJzDMebcAJoEG0yWtXAzvAaUg.mlCs8Uob1lBL5HvtohOLfj4puzKSTnlnkiyaidheZMEg.PNG.hye0702won/profileImage.png"
          },
          {
            "sid": "38281188",
            "bodySummary": "풀그라운드는 앞서 말씀 드렸다싶이 서울로7017 근처에 있는 음식점인데요 서울로에서 서쪽으로 내려가 실로암사우나를 오른쪽에 두고 앞으로 조금 올라가다 보면 있어요. 옆에 서브웨이 ",
            "url": "https://m.blog.naver.com/youphototravel/221372229040",
            "nick": "유포트",
            "profileImg": "http://blogpfthumb.phinf.naver.net/MjAxODExMDNfMTEg/MDAxNTQxMjE4Njg2ODQ0.O4uraHCUlE0_TdrOM7NwVY1qnerEW32A7A44V3jJA3Yg._RTo2OxiFbQJiabNgbDXEnEljsZP4RsLWbZKOPrie2og.JPEG.youphototravel/1.jpg"
          }
        ]
      }
    ]
  }
}